{
  "t_id": "t_05",
  "video_id": "Qro3G8lKl0Y",
  "language": "es",
  "segments": [
    {
      "text": ".",
      "start": 0.0,
      "duration": 2.0,
      "start_hhmmss": "00:00:00",
      "end_hhmmss": "00:00:02"
    },
    {
      "text": "A finales del verano de 1940,",
      "start": 21.04,
      "duration": 2.200000000000003,
      "start_hhmmss": "00:00:21",
      "end_hhmmss": "00:00:23"
    },
    {
      "text": "la Alemania nazi controlaba prácticamente toda Europa.",
      "start": 23.36,
      "duration": 3.200000000000003,
      "start_hhmmss": "00:00:23",
      "end_hhmmss": "00:00:27"
    },
    {
      "text": "Desde 1936, Alemania había utilizado una combinación de intimidación política",
      "start": 26.56,
      "duration": 6.0000000000000036,
      "start_hhmmss": "00:00:27",
      "end_hhmmss": "00:00:33"
    },
    {
      "text": "y una serie de rápidos ataques militares, conocidos como la Blitzkrieg,",
      "start": 32.56,
      "duration": 4.0,
      "start_hhmmss": "00:00:33",
      "end_hhmmss": "00:00:37"
    },
    {
      "text": "para tomar un país tras otro.",
      "start": 36.56,
      "duration": 3.0,
      "start_hhmmss": "00:00:37",
      "end_hhmmss": "00:00:40"
    },
    {
      "text": "Austria, Checoslovaquia, Polonia, Noruega, Dinamarca, Holanda, Bélgica",
      "start": 40.56,
      "duration": 9.0,
      "start_hhmmss": "00:00:41",
      "end_hhmmss": "00:00:50"
    },
    {
      "text": "y finalmente Francia, se rindieron ante el poder de Hitler, que parecía ser invencible.",
      "start": 49.56,
      "duration": 6.0,
      "start_hhmmss": "00:00:50",
      "end_hhmmss": "00:00:56"
    },
    {
      "text": "Al otro lado del canal de la Mancha, Inglaterra estaba aislada y era vulnerable.",
      "start": 56.56,
      "duration": 5.0,
      "start_hhmmss": "00:00:57",
      "end_hhmmss": "00:01:02"
    },
    {
      "text": "Solamente la Unión Soviética permanecía fuera del control de los nazis,",
      "start": 62.56,
      "duration": 4.0,
      "start_hhmmss": "00:01:03",
      "end_hhmmss": "00:01:07"
    },
    {
      "text": "pero por miedo a la ambición rusa, Hitler empezó a planear su movimiento más arriesgado.",
      "start": 66.56,
      "duration": 6.0,
      "start_hhmmss": "00:01:07",
      "end_hhmmss": "00:01:13"
    },
    {
      "text": "Si la Blitzkrieg funcionara contra Rusia, toda Europa estaría bajo su control.",
      "start": 73.56,
      "duration": 6.0,
      "start_hhmmss": "00:01:14",
      "end_hhmmss": "00:01:20"
    },
    {
      "text": "Seba, Inglaterra, Francia",
      "start": 87.56,
      "duration": 3.0,
      "start_hhmmss": "00:01:28",
      "end_hhmmss": "00:01:31"
    },
    {
      "text": "Alemania, Bolonia, Inglaterra",
      "start": 91.56,
      "duration": 3.0,
      "start_hhmmss": "00:01:32",
      "end_hhmmss": "00:01:35"
    },
    {
      "text": "Alemania, Bolonia, Inglaterra",
      "start": 95.56,
      "duration": 3.0,
      "start_hhmmss": "00:01:36",
      "end_hhmmss": "00:01:39"
    },
    {
      "text": "Alemania, Bolonia, Inglaterra",
      "start": 99.56,
      "duration": 3.0,
      "start_hhmmss": "00:01:40",
      "end_hhmmss": "00:01:43"
    },
    {
      "text": "Segunda Guerra Mundial",
      "start": 104.56,
      "duration": 3.0,
      "start_hhmmss": "00:01:45",
      "end_hhmmss": "00:01:48"
    },
    {
      "text": "Guerra Relámpago",
      "start": 107.56,
      "duration": 3.0,
      "start_hhmmss": "00:01:48",
      "end_hhmmss": "00:01:51"
    },
    {
      "text": "Rusia",
      "start": 111.56,
      "duration": 3.0,
      "start_hhmmss": "00:01:52",
      "end_hhmmss": "00:01:55"
    },
    {
      "text": "Adolf Hitler estaba obsesionado con exterminar a la raza eslava del este de Europa.",
      "start": 116.56,
      "duration": 5.0,
      "start_hhmmss": "00:01:57",
      "end_hhmmss": "00:02:02"
    },
    {
      "text": "Se refería a los eslavos como degenerados y esclavos de nacimiento que no merecían vivir.",
      "start": 121.56,
      "duration": 5.0,
      "start_hhmmss": "00:02:02",
      "end_hhmmss": "00:02:07"
    },
    {
      "text": "Con Europa central y Europa occidental en sus manos, y seguro de que Gran Bretaña estaba a punto de caer, Hitler centró su atención en Rusia.",
      "start": 127.56,
      "duration": 8.0,
      "start_hhmmss": "00:02:08",
      "end_hhmmss": "00:02:16"
    },
    {
      "text": "Hitler insistía a sus generales en que Alemania debía atacar pronto a Rusia,",
      "start": 136.56,
      "duration": 5.0,
      "start_hhmmss": "00:02:17",
      "end_hhmmss": "00:02:22"
    },
    {
      "text": "el tiempo que tardara permitiría al dictador ruso Josef Stalin reunir su propio ejército y atacar Alemania.",
      "start": 141.56,
      "duration": 7.0,
      "start_hhmmss": "00:02:22",
      "end_hhmmss": "00:02:29"
    },
    {
      "text": "Por una vez las sospechas de Hitler eran fundadas.",
      "start": 150.56,
      "duration": 3.0,
      "start_hhmmss": "00:02:31",
      "end_hhmmss": "00:02:34"
    },
    {
      "text": "Stalin sabía que Hitler era una amenaza y sólo un ejército débil y mal preparado le impedía marchar contra Alemania.",
      "start": 154.56,
      "duration": 7.0,
      "start_hhmmss": "00:02:35",
      "end_hhmmss": "00:02:42"
    },
    {
      "text": "Los dos grandes dictadores empezaron a jugar a un peligroso juego del gato y el ratón.",
      "start": 162.56,
      "duration": 5.0,
      "start_hhmmss": "00:02:43",
      "end_hhmmss": "00:02:48"
    },
    {
      "text": "Hitler sabía que Stalin, acostumbrado a intimidar y amenazar a sus víctimas hasta someterlas, no sucumbiría a la presión.",
      "start": 168.56,
      "duration": 7.0,
      "start_hhmmss": "00:02:49",
      "end_hhmmss": "00:02:56"
    },
    {
      "text": "Habría que impuirle un falso sentimiento de seguridad, por lo menos hasta que los alemanes reunieran las fuerzas necesarias para invadir las vastas extensiones de Rusia.",
      "start": 176.56,
      "duration": 9.0,
      "start_hhmmss": "00:02:57",
      "end_hhmmss": "00:03:06"
    },
    {
      "text": "A pesar de haber declarado en varias ocasiones que la cooperación con Rusia era impensable,",
      "start": 188.56,
      "duration": 4.0,
      "start_hhmmss": "00:03:09",
      "end_hhmmss": "00:03:13"
    },
    {
      "text": "Hitler empezó a negociar un tratado de no agresión y acuerdos comerciales con Rusia en el verano de 1939.",
      "start": 192.56,
      "duration": 7.0,
      "start_hhmmss": "00:03:13",
      "end_hhmmss": "00:03:20"
    },
    {
      "text": "Estableciendo esferas de influencia, los dos dictadores empezaron a repartirse la Europa del Este.",
      "start": 200.56,
      "duration": 5.0,
      "start_hhmmss": "00:03:21",
      "end_hhmmss": "00:03:26"
    },
    {
      "text": "Alemania invadió Polonia y cedió sus provincias orientales a Rusia.",
      "start": 206.56,
      "duration": 4.0,
      "start_hhmmss": "00:03:27",
      "end_hhmmss": "00:03:31"
    },
    {
      "text": "Stalin ocupó Letonia, Lituania, Estonia y gran parte de Finlandia y Alemania ocupó Noruega.",
      "start": 211.56,
      "duration": 7.0,
      "start_hhmmss": "00:03:32",
      "end_hhmmss": "00:03:39"
    },
    {
      "text": "Como parte de los acuerdos comerciales, Rusia debía proporcionar a Alemania grandes cantidades de grano y materias primas,",
      "start": 223.56,
      "duration": 7.0,
      "start_hhmmss": "00:03:44",
      "end_hhmmss": "00:03:51"
    },
    {
      "text": "mientras que los alemanes prometieron proporcionar asistencia técnica y armamento a Rusia.",
      "start": 231.56,
      "duration": 4.0,
      "start_hhmmss": "00:03:52",
      "end_hhmmss": "00:03:56"
    },
    {
      "text": "Los alemanes no tenían ninguna intención de mantener su promesa.",
      "start": 238.56,
      "duration": 3.0,
      "start_hhmmss": "00:03:59",
      "end_hhmmss": "00:04:02"
    },
    {
      "text": "El material que prometieron proporcionar, incluidos cruceros navales, tanques, Messerschmitts Me 109 y bombarderos pesados Heinkels, nunca fueron enviados.",
      "start": 242.56,
      "duration": 9.0,
      "start_hhmmss": "00:04:03",
      "end_hhmmss": "00:04:12"
    },
    {
      "text": "Hitler no tenía ninguna intención de armar a su siguiente víctima.",
      "start": 252.56,
      "duration": 4.0,
      "start_hhmmss": "00:04:13",
      "end_hhmmss": "00:04:17"
    },
    {
      "text": "Stalin mantuvo las apariencias y cumplió con su parte del trato, lenta pero concienzudamente.",
      "start": 256.56,
      "duration": 7.0,
      "start_hhmmss": "00:04:17",
      "end_hhmmss": "00:04:24"
    },
    {
      "text": "Entre febrero de 1940 y junio de 1941, Rusia entregó casi dos millones de toneladas de grano y otras dos toneladas de depresión.",
      "start": 264.56,
      "duration": 9.0,
      "start_hhmmss": "00:04:25",
      "end_hhmmss": "00:04:34"
    },
    {
      "text": "Estableciendo esferas de influencia, los dos dictadores empezaron a repartirse la Europa del Este.",
      "start": 274.56,
      "duration": 7.0,
      "start_hhmmss": "00:04:35",
      "end_hhmmss": "00:04:42"
    },
    {
      "text": "En 1941, Rusia entregó casi dos millones de toneladas de grano y otras dos toneladas de derivados del petróleo, elementos vitales para la maquinaria de guerra alemana.",
      "start": 281.56,
      "duration": 9.0,
      "start_hhmmss": "00:04:42",
      "end_hhmmss": "00:04:51"
    },
    {
      "text": "La verdad era que Stalin no tenía más remedio que contentar a los nazis.",
      "start": 297.56,
      "duration": 3.0,
      "start_hhmmss": "00:04:58",
      "end_hhmmss": "00:05:01"
    },
    {
      "text": "El ejército ruso era un completo desastre. En un ataque de paranoia, Stalin había ordenado la ejecución de 35.000 de sus oficiales más experimentados desde mediados de 1937 y finales de 1938.",
      "start": 301.56,
      "duration": 14.0,
      "start_hhmmss": "00:05:02",
      "end_hhmmss": "00:05:16"
    },
    {
      "text": "Ahora el ejército ruso estaba encabezado por oficiales con más ambición política que experiencia y el resto de las Fuerzas Armadas estaban demasiado aterrorizadas como para funcionar.",
      "start": 316.56,
      "duration": 10.0,
      "start_hhmmss": "00:05:17",
      "end_hhmmss": "00:05:27"
    },
    {
      "text": "Hasta que el ejército ruso fuera reconstruido, Stalin no tenía más remedio que apaciguar a Hitler y mantener a raya a los lobos alemanes.",
      "start": 327.56,
      "duration": 7.0,
      "start_hhmmss": "00:05:28",
      "end_hhmmss": "00:05:35"
    },
    {
      "text": "Oficialmente, el Partido Comunista consideraba que una invasión alemana era imposible.",
      "start": 337.56,
      "duration": 5.0,
      "start_hhmmss": "00:05:38",
      "end_hhmmss": "00:05:43"
    },
    {
      "text": "Personalmente, Stalin sabía que solo era cuestión de tiempo que tuviera que enfrentarse a Hitler en el campo de batalla, pero necesitaba dos o tres años para formar una defensa creíble.",
      "start": 343.56,
      "duration": 10.0,
      "start_hhmmss": "00:05:44",
      "end_hhmmss": "00:05:54"
    },
    {
      "text": "Enfrascadas en esta danza de muerte, Alemania y Rusia maniobraban para ser los primeros en golpear.",
      "start": 354.56,
      "duration": 7.0,
      "start_hhmmss": "00:05:55",
      "end_hhmmss": "00:06:02"
    },
    {
      "text": "Para mantener a Stalin en jaque, Hitler firmó tratados con las partes de Finlandia que Rusia no había ocupado y con Rumanía, territorios que proporcionaban posiciones ideales desde las que lanzar una invasión.",
      "start": 367.56,
      "duration": 13.0,
      "start_hhmmss": "00:06:08",
      "end_hhmmss": "00:06:21"
    },
    {
      "text": "Para esconder sus verdaderas intenciones, Hitler invitó a Vyacheslav Molotov, el ministro de Exteriores soviético, a Alemania en julio de 1940 para entablar unas conversaciones de paz e incluso sugirió que Rusia se unirá formalmente a las potencias del eje Alemania, Italia y Japón.",
      "start": 384.56,
      "duration": 19.0,
      "start_hhmmss": "00:06:25",
      "end_hhmmss": "00:06:44"
    },
    {
      "text": "A los rusos solo les interesaba saber por qué había tropas alemanas en Finlandia y Rumanía.",
      "start": 404.56,
      "duration": 5.0,
      "start_hhmmss": "00:06:45",
      "end_hhmmss": "00:06:50"
    },
    {
      "text": "Ambas partes hablaban, pero ninguna escuchaba y ninguna decía la verdad.",
      "start": 410.56,
      "duration": 6.0,
      "start_hhmmss": "00:06:51",
      "end_hhmmss": "00:06:57"
    },
    {
      "text": "La delicada tregua se estaba rompiendo y Hitler sabía que tenía que moverse rápido o la Blitzkrieg contra Rusia perdería el elemento sorpresa que era crucial.",
      "start": 419.56,
      "duration": 10.0,
      "start_hhmmss": "00:07:00",
      "end_hhmmss": "00:07:10"
    },
    {
      "text": "Hitler reunió a su alto mando y le presentó su plan.",
      "start": 434.56,
      "duration": 3.0,
      "start_hhmmss": "00:07:15",
      "end_hhmmss": "00:07:18"
    },
    {
      "text": "Emulando anteriores operaciones de la Blitzkrieg, tanques y bombarderos en picado realizarían una serie de profundas avanzadillas en territorio enemigo dividiendo y rodeando a las fuerzas rusas.",
      "start": 439.56,
      "duration": 10.0,
      "start_hhmmss": "00:07:20",
      "end_hhmmss": "00:07:30"
    },
    {
      "text": "Inmediatamente detrás de las fuerzas de avanzada vendría la infantería que eliminaría cualquier foco de tropas rusas que hubiera sobrevivido.",
      "start": 452.56,
      "duration": 7.0,
      "start_hhmmss": "00:07:33",
      "end_hhmmss": "00:07:40"
    },
    {
      "text": "Horrorizados ante la idea de tener que ocupar el oeste de Europa a la vez que entraban en las vastas extensiones de Rusia, los generales insistieron en que el consumo de los soldados y la maquinaria hacía imposible ganar la guerra en dos frentes.",
      "start": 460.56,
      "duration": 13.0,
      "start_hhmmss": "00:07:41",
      "end_hhmmss": "00:07:54"
    },
    {
      "text": "Esto mismo había costado a Alemania la primera guerra mundial y esta vez se saldaría con idéntico resultado.",
      "start": 474.56,
      "duration": 6.0,
      "start_hhmmss": "00:07:55",
      "end_hhmmss": "00:08:01"
    },
    {
      "text": "Pero Hitler hizo caso omiso de sus protestas.",
      "start": 481.56,
      "duration": 2.0,
      "start_hhmmss": "00:08:02",
      "end_hhmmss": "00:08:04"
    },
    {
      "text": "Esta era su guerra y la haría como le parecía conveniente.",
      "start": 484.56,
      "duration": 3.0,
      "start_hhmmss": "00:08:05",
      "end_hhmmss": "00:08:08"
    },
    {
      "text": "El plan, nombre en clave, Operación Parbarroja, se llevaría a cabo en la primavera de 1941.",
      "start": 488.56,
      "duration": 6.0,
      "start_hhmmss": "00:08:09",
      "end_hhmmss": "00:08:15"
    },
    {
      "text": "En diciembre de 1940 el plan había sido finalizado.",
      "start": 495.56,
      "duration": 3.0,
      "start_hhmmss": "00:08:16",
      "end_hhmmss": "00:08:19"
    },
    {
      "text": "Tres ejércitos enormes llevarían a cabo la invasión.",
      "start": 499.56,
      "duration": 3.0,
      "start_hhmmss": "00:08:20",
      "end_hhmmss": "00:08:23"
    },
    {
      "text": "Uno por el norte que debía penetrar en territorio ruso y asegurar la costa del Báltico y Leningrado.",
      "start": 503.56,
      "duration": 4.0,
      "start_hhmmss": "00:08:24",
      "end_hhmmss": "00:08:28"
    },
    {
      "text": "Otro se dirigiría hacia Moscú a través de Polonia.",
      "start": 508.56,
      "duration": 3.0,
      "start_hhmmss": "00:08:29",
      "end_hhmmss": "00:08:32"
    },
    {
      "text": "Y un tercero ocuparía las zonas industriales y agrícolas de Ucrania.",
      "start": 511.56,
      "duration": 3.999999999999943,
      "start_hhmmss": "00:08:32",
      "end_hhmmss": "00:08:36"
    },
    {
      "text": "Las tropas del frente ruso debían ser atacadas repetidamente con tal violencia que no pudieran ni pedir refuerzos ni retirarse hacia el interior de Rusia.",
      "start": 517.56,
      "duration": 8.0,
      "start_hhmmss": "00:08:38",
      "end_hhmmss": "00:08:46"
    },
    {
      "text": "Se esperaba que Rusia cayese en dos meses.",
      "start": 528.56,
      "duration": 3.0,
      "start_hhmmss": "00:08:49",
      "end_hhmmss": "00:08:52"
    },
    {
      "text": "Una invasión de estas dimensiones requería un ejército enorme.",
      "start": 541.56,
      "duration": 3.0,
      "start_hhmmss": "00:09:02",
      "end_hhmmss": "00:09:05"
    },
    {
      "text": "El 80% del ejército alemán atacaría Rusia dejando solamente un mínimo de fuerzas en los países ocupados de la Europa Occidental.",
      "start": 545.56,
      "duration": 7.0,
      "start_hhmmss": "00:09:06",
      "end_hhmmss": "00:09:13"
    },
    {
      "text": "La carga que la campaña de Rusia supuso para la capacidad de producción de Alemania debería haber sido evidente para Hitler y su aldea.",
      "start": 558.56,
      "duration": 8.0,
      "start_hhmmss": "00:09:19",
      "end_hhmmss": "00:09:27"
    },
    {
      "text": "La fuerza media de una división panzer bajó de 258 tanques a tan solo 196, pero Hitler no escuchaba a nadie.",
      "start": 566.56,
      "duration": 9.0,
      "start_hhmmss": "00:09:27",
      "end_hhmmss": "00:09:36"
    },
    {
      "text": "A las pocas horas de la finalización del plan, esta gran fuerza de la guerra de Rusia se desplazó.",
      "start": 582.56,
      "duration": 6.0,
      "start_hhmmss": "00:09:43",
      "end_hhmmss": "00:09:49"
    },
    {
      "text": "A las pocas horas de la finalización del plan, Stalin ya conocía las intenciones de Hitler.",
      "start": 588.56,
      "duration": 4.0,
      "start_hhmmss": "00:09:49",
      "end_hhmmss": "00:09:53"
    },
    {
      "text": "De hecho, entre mediados de diciembre de 1940 y junio de 1941, Joseph Stalin había sido avisado más de 80 veces, pero se negó a tomar medidas defensivas que pudieran provocar a Alemania.",
      "start": 593.56,
      "duration": 12.0,
      "start_hhmmss": "00:09:54",
      "end_hhmmss": "00:10:06"
    },
    {
      "text": "No se realizaron vuelos de reconocimiento sobre todo en el país.",
      "start": 606.56,
      "duration": 4.0,
      "start_hhmmss": "00:10:07",
      "end_hhmmss": "00:10:11"
    },
    {
      "text": "Y los aviones espía alemanes que sobrevolaban Rusia no fueron derribados.",
      "start": 610.56,
      "duration": 4.0,
      "start_hhmmss": "00:10:11",
      "end_hhmmss": "00:10:15"
    },
    {
      "text": "A pesar de la dureza inicial de las blitzkriegs anteriores, Stalin pudo pensar que en el caso de Rusia cualquier ataque a gran escala iría precedido de pequeños ataques protagonizados por las unidades de avance.",
      "start": 617.56,
      "duration": 10.0,
      "start_hhmmss": "00:10:18",
      "end_hhmmss": "00:10:28"
    },
    {
      "text": "O quizás por el ataque a Rusia a la unidad de avance, que se ha convertido en un ataque a Rusia a la unidad de avance.",
      "start": 628.56,
      "duration": 7.0,
      "start_hhmmss": "00:10:29",
      "end_hhmmss": "00:10:36"
    },
    {
      "text": "O quizás pensó que si parecía dócil, quizás conseguiría retrasar lo suficiente a Hitler como para montar su propia campaña.",
      "start": 635.56,
      "duration": 7.0,
      "start_hhmmss": "00:10:36",
      "end_hhmmss": "00:10:43"
    },
    {
      "text": "En cualquier caso, el ejército ruso estaba tristemente poco preparado para enfrentarse a una invasión.",
      "start": 643.56,
      "duration": 6.0,
      "start_hhmmss": "00:10:44",
      "end_hhmmss": "00:10:50"
    },
    {
      "text": "Mientras tanto, los soldados y el equipo alemanes avanzaban hacia el este.",
      "start": 654.56,
      "duration": 4.0,
      "start_hhmmss": "00:10:55",
      "end_hhmmss": "00:10:59"
    },
    {
      "text": "Durante tres meses, las tropas alemanas se desplegaron a lo largo de la orilla occidental del río Bug, la línea de demarcación entre las secciones de Polonia ocupadas por Alemania y Rusia.",
      "start": 658.56,
      "duration": 9.0,
      "start_hhmmss": "00:10:59",
      "end_hhmmss": "00:11:08"
    },
    {
      "text": "En el norte, se reunieron cerca del Báltico y en el sur a lo largo de la ruta hacia el Mar Negro.",
      "start": 669.56,
      "duration": 5.0,
      "start_hhmmss": "00:11:10",
      "end_hhmmss": "00:11:15"
    },
    {
      "text": "La línea de cañones, tanques y hombres se prolongaba a lo largo de 1900 kilómetros.",
      "start": 676.56,
      "duration": 5.0,
      "start_hhmmss": "00:11:17",
      "end_hhmmss": "00:11:22"
    },
    {
      "text": "El 19 de junio había más de tres millones de soldados alemanes, 600.000 vehículos, incluidos 3.500 tanques y tres cuartos de millón de caballos en posición para invadir Rusia.",
      "start": 681.56,
      "duration": 9.0,
      "start_hhmmss": "00:11:22",
      "end_hhmmss": "00:11:31"
    },
    {
      "text": "Escondidos en bosques, acequias, Recorderas, narcotr größas...",
      "start": 690.56,
      "duration": 5.0,
      "start_hhmmss": "00:11:31",
      "end_hhmmss": "00:11:36"
    },
    {
      "text": "... synthesis de tidy brazos, personalmente,oshop esle Beat fear著 la Often user gurak de guerra con los cho protective personality Internet.",
      "start": 700.56,
      "duration": 8.0,
      "start_hhmmss": "00:11:41",
      "end_hhmmss": "00:11:49"
    },
    {
      "text": "Yah Beyond, un del nutrimiento más Wissenschaftiska, fue Director de Teatro!)",
      "start": 710.56,
      "duration": 9.0,
      "start_hhmmss": "00:11:51",
      "end_hhmmss": "00:12:00"
    },
    {
      "text": "y campos de maíz, los soldados envolvían sus armas y bayonetas con trozos de sábanas",
      "start": 720.56,
      "duration": 5.039999999999964,
      "start_hhmmss": "00:12:01",
      "end_hhmmss": "00:12:06"
    },
    {
      "text": "para amortiguar cualquier sonido. Y evitaron las comunicaciones por radio, en algunos puntos",
      "start": 725.5999999999999,
      "duration": 5.840000000000032,
      "start_hhmmss": "00:12:06",
      "end_hhmmss": "00:12:11"
    },
    {
      "text": "los guarda rusos estaban a unos pocos metros.",
      "start": 731.4399999999999,
      "duration": 6.759999999999991,
      "start_hhmmss": "00:12:11",
      "end_hhmmss": "00:12:18"
    },
    {
      "text": "El ejército ruso, a pesar de contar con más de 5 millones de hombres, estaba poco",
      "start": 738.1999999999999,
      "duration": 4.480000000000018,
      "start_hhmmss": "00:12:18",
      "end_hhmmss": "00:12:23"
    },
    {
      "text": "preparado y mal equipado. De los 24.000 tanques rusos, sólo 1.500 no eran excesivamente",
      "start": 742.68,
      "duration": 6.0,
      "start_hhmmss": "00:12:23",
      "end_hhmmss": "00:12:29"
    },
    {
      "text": "obsoletos y sólo una cuarta parte de estos estaban en buenas condiciones.",
      "start": 748.68,
      "duration": 5.720000000000027,
      "start_hhmmss": "00:12:29",
      "end_hhmmss": "00:12:34"
    },
    {
      "text": "Muchos de los hombres no tenían armas y los que las tenían contaban con poca munición",
      "start": 754.4,
      "duration": 5.0,
      "start_hhmmss": "00:12:34",
      "end_hhmmss": "00:12:39"
    },
    {
      "text": "y todos tenían órdenes estrictas de no provocar ni tomar represalias ante un ataque alemán.",
      "start": 759.4,
      "duration": 5.0,
      "start_hhmmss": "00:12:39",
      "end_hhmmss": "00:12:44"
    },
    {
      "text": "A la 1 en punto de la madrugada del 22 de junio, la noche más corta del año, infiltrados",
      "start": 778.68,
      "duration": 12.440000000000055,
      "start_hhmmss": "00:12:59",
      "end_hhmmss": "00:13:11"
    },
    {
      "text": "alemanes cruzaron la frontera a escondidas y empezaron a cortar líneas telefónicas",
      "start": 791.12,
      "duration": 4.639999999999986,
      "start_hhmmss": "00:13:11",
      "end_hhmmss": "00:13:16"
    },
    {
      "text": "y a asesinar a los centinelas de los pasos fronterizos más solitarios. Dos horas más",
      "start": 795.76,
      "duration": 4.7999999999999545,
      "start_hhmmss": "00:13:16",
      "end_hhmmss": "00:13:21"
    },
    {
      "text": "se abrieron las puertas del infierno. Cuando amaneció en Polonia, cientos de bombarderos",
      "start": 801.56,
      "duration": 10.080000000000041,
      "start_hhmmss": "00:13:22",
      "end_hhmmss": "00:13:32"
    },
    {
      "text": "en picados tucca entraron en territorio ruso. Sus bombas de fragmentación destrozaron",
      "start": 811.64,
      "duration": 5.519999999999982,
      "start_hhmmss": "00:13:32",
      "end_hhmmss": "00:13:37"
    },
    {
      "text": "carreteras, depósitos de combustible y tanques aparicados en sus recintos.",
      "start": 817.16,
      "duration": 10.039999999999964,
      "start_hhmmss": "00:13:37",
      "end_hhmmss": "00:13:47"
    },
    {
      "text": "En cuanto los aviones dejaron caer las bombas y regresaron hacia la frontera, 6.000 cañones",
      "start": 827.2,
      "duration": 4.759999999999991,
      "start_hhmmss": "00:13:47",
      "end_hhmmss": "00:13:52"
    },
    {
      "text": "de campaña empezaron a disparar a puestos avanzados rusos, depósitos de provisiones",
      "start": 831.96,
      "duration": 4.680000000000064,
      "start_hhmmss": "00:13:52",
      "end_hhmmss": "00:13:57"
    },
    {
      "text": "y cuarteles.",
      "start": 836.6400000000001,
      "duration": 1.0,
      "start_hhmmss": "00:13:57",
      "end_hhmmss": "00:13:58"
    },
    {
      "text": "Ahora tras ahora, la luz base y la artillería se tornaban para atacar las líneas rusas.",
      "start": 837.64,
      "duration": 23.840000000000032,
      "start_hhmmss": "00:13:58",
      "end_hhmmss": "00:14:21"
    },
    {
      "text": "El ataque más largo de toda la historia había empezado a la hora prevista. Durante el ataque,",
      "start": 861.6,
      "duration": 8.399999999999977,
      "start_hhmmss": "00:14:22",
      "end_hhmmss": "00:14:30"
    },
    {
      "text": "grupos de asalto alemanes tomaron posesión de puentes que estaban en manos de los rusos,",
      "start": 870.0,
      "duration": 4.240000000000009,
      "start_hhmmss": "00:14:30",
      "end_hhmmss": "00:14:34"
    },
    {
      "text": "matando a los guardias antes de que pudieran destruir sus propios puentes o defenderse.",
      "start": 874.24,
      "duration": 4.519999999999982,
      "start_hhmmss": "00:14:34",
      "end_hhmmss": "00:14:39"
    },
    {
      "text": "A lo largo de un frente de casi 1.300 kilómetros, las divisiones de los grupos norte y central",
      "start": 878.76,
      "duration": 8.800000000000068,
      "start_hhmmss": "00:14:39",
      "end_hhmmss": "00:14:48"
    },
    {
      "text": "del ejército alemán avanzaban hacia Rusia. El ataque fue tan repentino y tan extraordinario",
      "start": 887.56,
      "duration": 5.840000000000032,
      "start_hhmmss": "00:14:48",
      "end_hhmmss": "00:14:53"
    },
    {
      "text": "que el ejército ruso empezó a caer casi de inmediato. Las comunicaciones se cortaron",
      "start": 893.4,
      "duration": 4.600000000000023,
      "start_hhmmss": "00:14:53",
      "end_hhmmss": "00:14:58"
    },
    {
      "text": "en cuanto los enclaves armados, los puestos de mando y en algunos casos divisiones enteras",
      "start": 898.0,
      "duration": 4.9799999999999045,
      "start_hhmmss": "00:14:58",
      "end_hhmmss": "00:15:03"
    },
    {
      "text": "desaparecieron en nubes de humo y metralla. El ataque penetró en territorio ruso con tal",
      "start": 902.9799999999999,
      "duration": 7.180000000000064,
      "start_hhmmss": "00:15:03",
      "end_hhmmss": "00:15:10"
    },
    {
      "text": "rapidez que las unidades motorizadas y los tanques alemanes adelantaron a las tropas",
      "start": 910.16,
      "duration": 5.039999999999964,
      "start_hhmmss": "00:15:10",
      "end_hhmmss": "00:15:15"
    },
    {
      "text": "rusas que aún estaban recibiendo instrucciones de última hora. Lo que más sorprendió a",
      "start": 915.2,
      "duration": 5.720000000000027,
      "start_hhmmss": "00:15:15",
      "end_hhmmss": "00:15:21"
    },
    {
      "text": "los alemanes fue la absoluta falta de respuesta. Los rusos casi ni intentaron contraatacar",
      "start": 920.9200000000001,
      "duration": 6.079999999999927,
      "start_hhmmss": "00:15:21",
      "end_hhmmss": "00:15:27"
    },
    {
      "text": "ni retirarse, simplemente se quedaron donde estaban y murieron entre una lluvia de balas",
      "start": 927.0,
      "duration": 6.080000000000041,
      "start_hhmmss": "00:15:27",
      "end_hhmmss": "00:15:33"
    },
    {
      "text": "y bombas. A Moscú llegaban informes de devastación uno tras otro, pero las órdenes de Stalin",
      "start": 933.08,
      "duration": 15.519999999999982,
      "start_hhmmss": "00:15:33",
      "end_hhmmss": "00:15:49"
    },
    {
      "text": "no cambiaban, no provocara a los alemanes. Los cazarrusos eran destruidos en tierra o",
      "start": 948.6,
      "duration": 18.519999999999982,
      "start_hhmmss": "00:15:49",
      "end_hhmmss": "00:16:07"
    },
    {
      "text": "despedazados en cuanto despegaban para ir a defender la frontera. En cuestión de horas",
      "start": 967.12,
      "duration": 5.240000000000009,
      "start_hhmmss": "00:16:07",
      "end_hhmmss": "00:16:12"
    },
    {
      "text": "Los alemanes controlaban la tierra y los cielos. Cuatro horas después del inicio del ataque,",
      "start": 972.52,
      "duration": 11.0,
      "start_hhmmss": "00:16:13",
      "end_hhmmss": "00:16:24"
    },
    {
      "text": "Stalin cedió. Las tropas rusas debían hacer retroceder a los alemanes hasta el otro lado",
      "start": 983.52,
      "duration": 5.060000000000059,
      "start_hhmmss": "00:16:24",
      "end_hhmmss": "00:16:29"
    },
    {
      "text": "de la frontera, pero ya era demasiado tarde, la línea de frente rusa ya no existía. Lo",
      "start": 988.58,
      "duration": 7.3799999999999955,
      "start_hhmmss": "00:16:29",
      "end_hhmmss": "00:16:36"
    },
    {
      "text": "mejor que podían hacer los rusos ahora era organizar una retirada. Todos los intentos",
      "start": 995.96,
      "duration": 4.7999999999999545,
      "start_hhmmss": "00:16:36",
      "end_hhmmss": "00:16:41"
    },
    {
      "text": "de estabilizar las dispersas líneas rusas fracasaron, las tropas eran presas del pánico",
      "start": 1000.76,
      "duration": 5.559999999999945,
      "start_hhmmss": "00:16:41",
      "end_hhmmss": "00:16:46"
    },
    {
      "text": "y las líneas de abastecimiento estaban tan mal organizadas que no servían de nada. Muchas",
      "start": 1006.3199999999999,
      "duration": 4.680000000000064,
      "start_hhmmss": "00:16:46",
      "end_hhmmss": "00:16:51"
    },
    {
      "text": "unidades ni siquiera tenían radio. Las tropas alemanas avanzaban tan rápido que incluso",
      "start": 1011.0,
      "duration": 11.67999999999995,
      "start_hhmmss": "00:16:51",
      "end_hhmmss": "00:17:03"
    },
    {
      "text": "ni los cuarteles generales alemanes podían hacer un seguimiento de sus tropas. El cuerpo",
      "start": 1022.68,
      "duration": 6.760000000000105,
      "start_hhmmss": "00:17:03",
      "end_hhmmss": "00:17:09"
    },
    {
      "text": "de ingenieros alemán construía puentes en menos de nueve horas, ofreciendo cada vez",
      "start": 1029.44,
      "duration": 4.119999999999891,
      "start_hhmmss": "00:17:09",
      "end_hhmmss": "00:17:14"
    },
    {
      "text": "más puntos por los que el equipo pesado podía cruzar los ríos. Por muy rápido que avanzara,",
      "start": 1033.56,
      "duration": 7.560000000000173,
      "start_hhmmss": "00:17:14",
      "end_hhmmss": "00:17:21"
    },
    {
      "text": "la infantería alemana no podía seguir el ritmo de las unidades motorizadas de los cuerpos",
      "start": 1041.1200000000001,
      "duration": 4.079999999999927,
      "start_hhmmss": "00:17:21",
      "end_hhmmss": "00:17:25"
    },
    {
      "text": "Panzer. Al final del primer día, los tanques alemanes habían recorrido más de 65 kilómetros",
      "start": 1045.2,
      "duration": 10.440000000000055,
      "start_hhmmss": "00:17:25",
      "end_hhmmss": "00:17:36"
    },
    {
      "text": "en territorio ruso. 1500 aviones rusos habían sido destruidos, muchos de ellos estando aún",
      "start": 1055.64,
      "duration": 5.880000000000109,
      "start_hhmmss": "00:17:36",
      "end_hhmmss": "00:17:42"
    },
    {
      "text": "en tierra, y tres divisiones soviéticas completas habían sido totalmente eliminadas. Mientras",
      "start": 1061.5200000000002,
      "duration": 9.039999999999964,
      "start_hhmmss": "00:17:42",
      "end_hhmmss": "00:17:51"
    },
    {
      "text": "el grupo central avanzaba a través de la parte soviética de Polonia, a 970 kilómetros",
      "start": 1070.5600000000002,
      "duration": 4.779999999999973,
      "start_hhmmss": "00:17:51",
      "end_hhmmss": "00:17:55"
    },
    {
      "text": "hacia el norte a lo largo de la costa báltica, el grupo norte había abierto una brecha de",
      "start": 1075.3400000000001,
      "duration": 4.7999999999999545,
      "start_hhmmss": "00:17:55",
      "end_hhmmss": "00:18:00"
    },
    {
      "text": "kilómetros de ancho en las líneas rusas y se estaba abriendo paso hacia Leningrado.",
      "start": 1080.74,
      "duration": 7.019999999999982,
      "start_hhmmss": "00:18:01",
      "end_hhmmss": "00:18:08"
    },
    {
      "text": "La invasión era una copia exacta de la invasión de Polonia en 1939, pero a una escala mayor",
      "start": 1087.76,
      "duration": 5.820000000000164,
      "start_hhmmss": "00:18:08",
      "end_hhmmss": "00:18:14"
    },
    {
      "text": "de lo que habría podido imaginarse. El 24 de junio, el tercer día de invasión, los",
      "start": 1093.5800000000002,
      "duration": 7.440000000000055,
      "start_hhmmss": "00:18:14",
      "end_hhmmss": "00:18:21"
    },
    {
      "text": "Panzers del grupo central estaban a tan solo 95 kilómetros de la ciudad de Minsk y los",
      "start": 1101.0200000000002,
      "duration": 5.479999999999791,
      "start_hhmmss": "00:18:21",
      "end_hhmmss": "00:18:26"
    },
    {
      "text": "ejércitos rusos que se encontraban allí. En una clásica maniobra de la Blitzkrieg,",
      "start": 1106.62,
      "duration": 7.0,
      "start_hhmmss": "00:18:27",
      "end_hhmmss": "00:18:34"
    },
    {
      "text": "los tanques se dispersaron para formar una enorme garra que debía cerrarse sobre Minsk.",
      "start": 1115.62,
      "duration": 7.0,
      "start_hhmmss": "00:18:36",
      "end_hhmmss": "00:18:43"
    },
    {
      "text": "Dentro de esta enorme garra de hierro, había otra más pequeña de infantería motorizada,",
      "start": 1129.86,
      "duration": 5.120000000000118,
      "start_hhmmss": "00:18:50",
      "end_hhmmss": "00:18:55"
    },
    {
      "text": "para devorar todo lo que quedara atrapado en el círculo de Panzers. 26 de junio, la",
      "start": 1135.34,
      "duration": 5.0,
      "start_hhmmss": "00:18:55",
      "end_hhmmss": "00:19:00"
    },
    {
      "text": "trampa se cerró al este de Minsk.",
      "start": 1140.34,
      "duration": 7.0,
      "start_hhmmss": "00:19:00",
      "end_hhmmss": "00:19:07"
    },
    {
      "text": "Cuando cayó Minsk, 32 de las 43 divisiones rusas que la defendían quedaron completamente",
      "start": 1165.54,
      "duration": 7.0,
      "start_hhmmss": "00:19:26",
      "end_hhmmss": "00:19:33"
    },
    {
      "text": "destrozadas. El resto de divisiones proporcionaron a los alemanes más de 300.000 prisioneros",
      "start": 1173.42,
      "duration": 7.0,
      "start_hhmmss": "00:19:33",
      "end_hhmmss": "00:19:40"
    },
    {
      "text": "y un botín de más de 3.000 tanques y 1.500 piezas de artillería.",
      "start": 1184.1,
      "duration": 7.0,
      "start_hhmmss": "00:19:44",
      "end_hhmmss": "00:19:51"
    },
    {
      "text": "El general ruso escapó al ataque alemán y se apresuró a llamar a Moscú para avisar",
      "start": 1195.6200000000001,
      "duration": 7.0,
      "start_hhmmss": "00:19:56",
      "end_hhmmss": "00:20:03"
    },
    {
      "text": "a sus superiores del inminente desastre. A Stalin no le gustaban las excusas y ordenó",
      "start": 1204.14,
      "duration": 6.720000000000027,
      "start_hhmmss": "00:20:04",
      "end_hhmmss": "00:20:11"
    },
    {
      "text": "que fusilaran al general. Con Minsk claramente bajo su control, el siguiente",
      "start": 1210.8600000000001,
      "duration": 7.0,
      "start_hhmmss": "00:20:11",
      "end_hhmmss": "00:20:18"
    },
    {
      "text": "objetivo del grupo central era Smolensk, a 300 kilómetros hacia el este, en la ruta",
      "start": 1218.86,
      "duration": 6.0,
      "start_hhmmss": "00:20:19",
      "end_hhmmss": "00:20:25"
    },
    {
      "text": "que llevaba directamente hacia Moscú. Smolensk cayó el 17 de julio, pero ahora los alemanes",
      "start": 1224.86,
      "duration": 7.0,
      "start_hhmmss": "00:20:25",
      "end_hhmmss": "00:20:32"
    },
    {
      "text": "tenían graves problemas. La Blitzkrieg se estaba quedando sin energía.",
      "start": 1234.26,
      "duration": 7.0,
      "start_hhmmss": "00:20:34",
      "end_hhmmss": "00:20:41"
    },
    {
      "text": "Por miedo a que sus tropas se estuvieran distanciando demasiado de sus líneas de abastecimiento,",
      "start": 1242.26,
      "duration": 7.0,
      "start_hhmmss": "00:20:42",
      "end_hhmmss": "00:20:49"
    },
    {
      "text": "Hitler les ordenó que se detuvieran en Minsk hasta que les llegaran refuerzos y provisiones.",
      "start": 1251.74,
      "duration": 7.0,
      "start_hhmmss": "00:20:52",
      "end_hhmmss": "00:20:59"
    },
    {
      "text": "Con el ejército alemán a tan solo 650 kilómetros de Moscú, Stalin tuvo que aceptar la realidad.",
      "start": 1262.3,
      "duration": 7.0,
      "start_hhmmss": "00:21:02",
      "end_hhmmss": "00:21:09"
    },
    {
      "text": "Dónde un llamamiento a su pueblo para que defendieran su amada madre Rusia. Habló",
      "start": 1269.3,
      "duration": 3.9200000000000728,
      "start_hhmmss": "00:21:09",
      "end_hhmmss": "00:21:13"
    },
    {
      "text": "de una gran guerra patriótica e instigó al pueblo a no dejar nada que pudiera ser",
      "start": 1273.22,
      "duration": 5.119999999999891,
      "start_hhmmss": "00:21:13",
      "end_hhmmss": "00:21:18"
    },
    {
      "text": "útil a los nazis. Todo lo que no pudieran poner a salvo debía ser destruido. Casas,",
      "start": 1278.34,
      "duration": 7.0,
      "start_hhmmss": "00:21:18",
      "end_hhmmss": "00:21:25"
    },
    {
      "text": "campos, bosques, todo debía quedar reducido a cenizas. El ejército en retirada ejecutaría",
      "start": 1285.34,
      "duration": 7.0,
      "start_hhmmss": "00:21:25",
      "end_hhmmss": "00:21:32"
    },
    {
      "text": "a aquellos propietarios que no estuvieran dispuestos a hacer tal sacrificio. En el interior",
      "start": 1292.34,
      "duration": 7.0,
      "start_hhmmss": "00:21:32",
      "end_hhmmss": "00:21:39"
    },
    {
      "text": "de la ciudad se encontraban los habitantes de los que se les había presentado. En el",
      "start": 1305.34,
      "duration": 7.0,
      "start_hhmmss": "00:21:45",
      "end_hhmmss": "00:21:52"
    },
    {
      "text": "interior de la ciudad se encontraban los habitantes de los que se les había presentado. En la",
      "start": 1314.74,
      "duration": 7.0,
      "start_hhmmss": "00:21:55",
      "end_hhmmss": "00:22:02"
    },
    {
      "text": "ciudad de Rusia, lejos del rumor de la batalla, trabajadores y unidades de reserva se entrenaban",
      "start": 1322.34,
      "duration": 4.920000000000073,
      "start_hhmmss": "00:22:02",
      "end_hhmmss": "00:22:07"
    },
    {
      "text": "en las tácticas de carrilla para ser enviados tras las líneas enemigas y hostigar a los",
      "start": 1327.26,
      "duration": 4.519999999999982,
      "start_hhmmss": "00:22:07",
      "end_hhmmss": "00:22:12"
    },
    {
      "text": "invasores desde la retaguardia. A pesar de las dificultades que se presentaron en la",
      "start": 1331.78,
      "duration": 7.0,
      "start_hhmmss": "00:22:12",
      "end_hhmmss": "00:22:19"
    },
    {
      "text": "pequeña molestia que provocaban los partisanos, los alemanes continuaron su imparable avance",
      "start": 1352.34,
      "duration": 5.039999999999964,
      "start_hhmmss": "00:22:32",
      "end_hhmmss": "00:22:37"
    },
    {
      "text": "sobre Rusia. El 10 de julio, solamente 18 días después del inicio de la invasión,",
      "start": 1357.3799999999999,
      "duration": 6.079999999999927,
      "start_hhmmss": "00:22:37",
      "end_hhmmss": "00:22:43"
    },
    {
      "text": "el grupo central estaba preparado para atacar Smolensk. Aún presos de la confusión por",
      "start": 1363.4599999999998,
      "duration": 7.0,
      "start_hhmmss": "00:22:43",
      "end_hhmmss": "00:22:50"
    },
    {
      "text": "el desastre de Minsk de hace dos semanas, los rusos fueron incapaces de preparar una",
      "start": 1372.8999999999999,
      "duration": 4.759999999999991,
      "start_hhmmss": "00:22:53",
      "end_hhmmss": "00:22:58"
    },
    {
      "text": "defensa organizada. Una vez más se utilizó la maniobra en pinza y una vez más funcionó.",
      "start": 1377.66,
      "duration": 7.0,
      "start_hhmmss": "00:22:58",
      "end_hhmmss": "00:23:05"
    },
    {
      "text": "Otros dos ejércitos soviéticos quedaron atrapados y fueron eliminados entre las ruinas",
      "start": 1396.66,
      "duration": 4.2000000000000455,
      "start_hhmmss": "00:23:17",
      "end_hhmmss": "00:23:21"
    },
    {
      "text": "de una ciudad rusa. El 16 de julio Smolensk capituló. Con una maniobra en pinza tras",
      "start": 1400.86,
      "duration": 7.0,
      "start_hhmmss": "00:23:21",
      "end_hhmmss": "00:23:28"
    },
    {
      "text": "otra los nazis estaban conquistando grandes extensiones de Rusia. Hitler y su ejército",
      "start": 1412.34,
      "duration": 5.759999999999991,
      "start_hhmmss": "00:23:32",
      "end_hhmmss": "00:23:38"
    },
    {
      "text": "veían la victoria al alcance de su mano. El paisaje estaba sembrado de los cuerpos",
      "start": 1418.1,
      "duration": 7.0,
      "start_hhmmss": "00:23:38",
      "end_hhmmss": "00:23:45"
    },
    {
      "text": "de medio millón de rusos muertos. Los prisioneros, marchando en columnas de seis, llegaban hasta",
      "start": 1426.1,
      "duration": 7.0,
      "start_hhmmss": "00:23:46",
      "end_hhmmss": "00:23:53"
    },
    {
      "text": "donde alcanzaba la vista y se dirigían a los campos de prisioneros de guerra alemanes.",
      "start": 1441.62,
      "duration": 6.279999999999973,
      "start_hhmmss": "00:24:02",
      "end_hhmmss": "00:24:08"
    },
    {
      "text": "Parecía que Rusia fuera a quedarse sin habitantes.",
      "start": 1447.8999999999999,
      "duration": 5.0,
      "start_hhmmss": "00:24:08",
      "end_hhmmss": "00:24:13"
    },
    {
      "text": "Pero tras tres agotadoras semanas abriéndose paso por media Polonia y hasta casi 800 kilómetros",
      "start": 1452.9,
      "duration": 7.0,
      "start_hhmmss": "00:24:13",
      "end_hhmmss": "00:24:20"
    },
    {
      "text": "dentro del territorio ruso, los hombres y las máquinas del grupo central también estaban",
      "start": 1474.26,
      "duration": 5.2800000000002,
      "start_hhmmss": "00:24:34",
      "end_hhmmss": "00:24:40"
    },
    {
      "text": "al límite. Cuando se detuvieron en las afueras de Smolensk",
      "start": 1479.54,
      "duration": 7.0,
      "start_hhmmss": "00:24:40",
      "end_hhmmss": "00:24:47"
    },
    {
      "text": "para reagruparse y esperar a que llegaran las provisiones en preparación para el ataque",
      "start": 1491.94,
      "duration": 4.279999999999973,
      "start_hhmmss": "00:24:52",
      "end_hhmmss": "00:24:56"
    },
    {
      "text": "final a Moscú, encontraron un frente de rusos decididos a no rendirse.",
      "start": 1496.22,
      "duration": 7.0,
      "start_hhmmss": "00:24:56",
      "end_hhmmss": "00:25:03"
    },
    {
      "text": "Incapaces de salvar Smolensk, los rusos establecieron su primera línea de defensa efectiva a",
      "start": 1509.54,
      "duration": 7.0,
      "start_hhmmss": "00:25:10",
      "end_hhmmss": "00:25:17"
    },
    {
      "text": "40 kilómetros al este de la ciudad, a tan solo 320 kilómetros de Moscú.",
      "start": 1524.26,
      "duration": 7.0,
      "start_hhmmss": "00:25:24",
      "end_hhmmss": "00:25:31"
    },
    {
      "text": "Durante ocho semanas el grupo central estuvo inmovilizado ante la resistencia rusa y con",
      "start": 1533.1,
      "duration": 4.680000000000064,
      "start_hhmmss": "00:25:33",
      "end_hhmmss": "00:25:38"
    },
    {
      "text": "escasas provisiones. Los rusos reunieron a sus mejores tropas y",
      "start": 1537.78,
      "duration": 7.0,
      "start_hhmmss": "00:25:38",
      "end_hhmmss": "00:25:45"
    },
    {
      "text": "las últimas tecnologías y arremetieron contra las tropas alemanas.",
      "start": 1548.98,
      "duration": 7.0,
      "start_hhmmss": "00:25:49",
      "end_hhmmss": "00:25:56"
    },
    {
      "text": "Los lanzacohetes múltiples Katyusha, de reciente creación, acribillaron a los alemanes con",
      "start": 1562.54,
      "duration": 4.920000000000073,
      "start_hhmmss": "00:26:03",
      "end_hhmmss": "00:26:07"
    },
    {
      "text": "fuego de artillería, destrozando a hombres y equipo con morteros cargados con cohetes.",
      "start": 1567.46,
      "duration": 7.0,
      "start_hhmmss": "00:26:07",
      "end_hhmmss": "00:26:14"
    },
    {
      "text": "Entonces los tanques soviéticos más modernos salieron de entre el humo, incluido el enorme",
      "start": 1582.38,
      "duration": 4.599999999999909,
      "start_hhmmss": "00:26:22",
      "end_hhmmss": "00:26:27"
    },
    {
      "text": "KV-2. Con un peso de casi 60 toneladas, era el vehículo",
      "start": 1586.98,
      "duration": 4.920000000000073,
      "start_hhmmss": "00:26:27",
      "end_hhmmss": "00:26:32"
    },
    {
      "text": "acorazado más grande jamás fabricado. Unos T-34 nuevos y relucientes acompañaban",
      "start": 1591.9,
      "duration": 7.0,
      "start_hhmmss": "00:26:32",
      "end_hhmmss": "00:26:39"
    },
    {
      "text": "a los KV-2. Recuiertos por un blindaje de 8 centímetros",
      "start": 1600.7800000000002,
      "duration": 5.399999999999864,
      "start_hhmmss": "00:26:41",
      "end_hhmmss": "00:26:46"
    },
    {
      "text": "de grosor eran inmunes a los proyectiles antitanque alemanes. Era como si los alemanes",
      "start": 1606.18,
      "duration": 5.279999999999973,
      "start_hhmmss": "00:26:46",
      "end_hhmmss": "00:26:51"
    },
    {
      "text": "dispararan balas de goma. Por suerte para los alemanes, los tanques",
      "start": 1611.46,
      "duration": 7.0,
      "start_hhmmss": "00:26:51",
      "end_hhmmss": "00:26:58"
    },
    {
      "text": "tribulantes eran tan ineptos como avanzada era su tecnología. Los KV-2 y los T-34 no",
      "start": 1621.9,
      "duration": 7.0,
      "start_hhmmss": "00:27:02",
      "end_hhmmss": "00:27:09"
    },
    {
      "text": "sabían luchar en formación, así que era fácil aislarlos y acercarse lo suficiente",
      "start": 1629.42,
      "duration": 4.480000000000018,
      "start_hhmmss": "00:27:09",
      "end_hhmmss": "00:27:14"
    },
    {
      "text": "para volarles las ruedas. Al final los alemanes triunfaron, pero el",
      "start": 1633.9,
      "duration": 5.720000000000027,
      "start_hhmmss": "00:27:14",
      "end_hhmmss": "00:27:20"
    },
    {
      "text": "grupo central no lo había tenido nada fácil.",
      "start": 1639.6200000000001,
      "duration": 7.0,
      "start_hhmmss": "00:27:20",
      "end_hhmmss": "00:27:27"
    },
    {
      "text": "Ante los nuevos acontecimientos, Hitler vaciló. Sabía perfectamente que la invasión de Rusia",
      "start": 1646.62,
      "duration": 7.0,
      "start_hhmmss": "00:27:27",
      "end_hhmmss": "00:27:34"
    },
    {
      "text": "no había sido planeada con la meticulosidad de las batallas anteriores. Ahora insistía",
      "start": 1654.9399999999998,
      "duration": 4.960000000000036,
      "start_hhmmss": "00:27:35",
      "end_hhmmss": "00:27:40"
    },
    {
      "text": "en que Moscú nunca había sido un objetivo estratégico.",
      "start": 1659.8999999999999,
      "duration": 4.240000000000009,
      "start_hhmmss": "00:27:40",
      "end_hhmmss": "00:27:44"
    },
    {
      "text": "El 30 de julio de 1941, a más de un mes del inicio de la invasión de Rusia, Hitler tomó",
      "start": 1664.1399999999999,
      "duration": 5.559999999999945,
      "start_hhmmss": "00:27:44",
      "end_hhmmss": "00:27:50"
    },
    {
      "text": "la primera de una serie de decisiones que probablemente le costarían la campaña y",
      "start": 1669.6999999999998,
      "duration": 4.400000000000091,
      "start_hhmmss": "00:27:50",
      "end_hhmmss": "00:27:54"
    },
    {
      "text": "a la larga la guerra. En lugar de permitir que el grupo central",
      "start": 1674.1799999999998,
      "duration": 5.680000000000064,
      "start_hhmmss": "00:27:54",
      "end_hhmmss": "00:28:00"
    },
    {
      "text": "continuara hacia Moscú, lo dividió y envió a la mitad hacia el norte para reforzar la",
      "start": 1679.86,
      "duration": 4.839999999999918,
      "start_hhmmss": "00:28:00",
      "end_hhmmss": "00:28:05"
    },
    {
      "text": "campaña de Leningrado y el resto hacia Ucrania.",
      "start": 1684.6999999999998,
      "duration": 7.0,
      "start_hhmmss": "00:28:05",
      "end_hhmmss": "00:28:12"
    },
    {
      "text": "Las tropas alemanas, exhaustas y a menos de 320 kilómetros de la capital soviética,",
      "start": 1694.1399999999999,
      "duration": 5.519999999999982,
      "start_hhmmss": "00:28:14",
      "end_hhmmss": "00:28:20"
    },
    {
      "text": "recibieron la orden de desplazarse a más de 965 kilómetros hacia el norte y el sur,",
      "start": 1699.66,
      "duration": 5.559999999999945,
      "start_hhmmss": "00:28:20",
      "end_hhmmss": "00:28:25"
    },
    {
      "text": "donde debían continuar luchando. La infantería ya iba a más de 160 kilómetros",
      "start": 1705.22,
      "duration": 5.920000000000073,
      "start_hhmmss": "00:28:25",
      "end_hhmmss": "00:28:31"
    },
    {
      "text": "por detrás de las unidades Panzer y algunas de las divisiones motorizadas estaban a más",
      "start": 1711.14,
      "duration": 5.0,
      "start_hhmmss": "00:28:31",
      "end_hhmmss": "00:28:36"
    },
    {
      "text": "de 320 kilómetros del depósito de combustible más cercano.",
      "start": 1716.14,
      "duration": 7.0,
      "start_hhmmss": "00:28:36",
      "end_hhmmss": "00:28:43"
    },
    {
      "text": "Y lo peor era que los alemanes tenían a 400.000 heridos y casi 100.000 muertos, más bajas",
      "start": 1723.14,
      "duration": 7.0,
      "start_hhmmss": "00:28:43",
      "end_hhmmss": "00:28:50"
    },
    {
      "text": "que en todas las demás batallas de la guerra juntas.",
      "start": 1732.14,
      "duration": 7.0,
      "start_hhmmss": "00:28:52",
      "end_hhmmss": "00:28:59"
    },
    {
      "text": "Mientras el grupo central avanzaba hacia Moscú, sus colegas del norte se dirigían",
      "start": 1739.14,
      "duration": 7.0,
      "start_hhmmss": "00:28:59",
      "end_hhmmss": "00:29:06"
    },
    {
      "text": "a Leningrado. El ataque de los viejos puertos rusos y la",
      "start": 1752.18,
      "duration": 7.0,
      "start_hhmmss": "00:29:12",
      "end_hhmmss": "00:29:19"
    },
    {
      "text": "vieja capital imperial debería haber sido rápido y sencillo. El grupo norte habría",
      "start": 1759.18,
      "duration": 7.0,
      "start_hhmmss": "00:29:19",
      "end_hhmmss": "00:29:26"
    },
    {
      "text": "atravesado Letonia, Lituania y Estonia y habría pasado por un corredor de tierra de 200 kilómetros",
      "start": 1766.3400000000001,
      "duration": 5.0,
      "start_hhmmss": "00:29:26",
      "end_hhmmss": "00:29:31"
    },
    {
      "text": "de ancho entre dos lagos para dirigirse directamente hacia Leningrado.",
      "start": 1771.3400000000001,
      "duration": 7.0,
      "start_hhmmss": "00:29:31",
      "end_hhmmss": "00:29:38"
    },
    {
      "text": "Situada entre el lago Ladoga y el Báltico, Leningrado era fácil de defender.",
      "start": 1779.38,
      "duration": 7.0,
      "start_hhmmss": "00:29:39",
      "end_hhmmss": "00:29:46"
    },
    {
      "text": "Pero una vez aislada sería casi imposible hacerle llegar provisiones.",
      "start": 1787.38,
      "duration": 7.0,
      "start_hhmmss": "00:29:47",
      "end_hhmmss": "00:29:54"
    },
    {
      "text": "La violencia del ataque alemán cogió completamente por sorpresa las tropas rusas en retirada",
      "start": 1801.3000000000002,
      "duration": 5.0,
      "start_hhmmss": "00:30:01",
      "end_hhmmss": "00:30:06"
    },
    {
      "text": "que huyeron en estampida y dejaron Leningrado peligrosamente desprotegida.",
      "start": 1806.3000000000002,
      "duration": 7.0,
      "start_hhmmss": "00:30:06",
      "end_hhmmss": "00:30:13"
    },
    {
      "text": "El 26 de junio, solo cuatro días después del inicio de la invasión, los tanques alemanes",
      "start": 1816.38,
      "duration": 7.0,
      "start_hhmmss": "00:30:16",
      "end_hhmmss": "00:30:23"
    },
    {
      "text": "habían recorrido casi 320 kilómetros en territorio ruso y estaban a menos de 480 kilómetros",
      "start": 1826.5400000000002,
      "duration": 6.679999999999836,
      "start_hhmmss": "00:30:27",
      "end_hhmmss": "00:30:33"
    },
    {
      "text": "de Leningrado. Un mes más tarde, Leningrado estaba a un",
      "start": 1833.22,
      "duration": 7.0,
      "start_hhmmss": "00:30:33",
      "end_hhmmss": "00:30:40"
    },
    {
      "text": "paso de la rendición y con 29 divisiones alemanas frente a una modesta defensa de",
      "start": 1840.22,
      "duration": 6.2000000000000455,
      "start_hhmmss": "00:30:40",
      "end_hhmmss": "00:30:46"
    },
    {
      "text": "15 divisiones rusas, la conquista de Leningrado debería haber sido cuestión de días.",
      "start": 1846.42,
      "duration": 7.0,
      "start_hhmmss": "00:30:46",
      "end_hhmmss": "00:30:53"
    },
    {
      "text": "Sin esperanzas de recibir refuerzos, el comandante de las tropas de Leningrado planeó una retirada",
      "start": 1857.26,
      "duration": 5.1400000000001,
      "start_hhmmss": "00:30:57",
      "end_hhmmss": "00:31:02"
    },
    {
      "text": "estratégica hacia el centro de la ciudad. Defendería en cada plaza, cada un de los",
      "start": 1862.4,
      "duration": 7.0,
      "start_hhmmss": "00:31:02",
      "end_hhmmss": "00:31:09"
    },
    {
      "text": "barones, cada calle, cada casa si fuera necesario.",
      "start": 1870.22,
      "duration": 7.0,
      "start_hhmmss": "00:31:10",
      "end_hhmmss": "00:31:17"
    },
    {
      "text": "Con la mayor parte de los barones adultos destinados al ejército, la ciudad dependía",
      "start": 1878.3,
      "duration": 4.440000000000055,
      "start_hhmmss": "00:31:18",
      "end_hhmmss": "00:31:23"
    },
    {
      "text": "de mujeres, niños y ancianos para construir sus defensas.",
      "start": 1882.74,
      "duration": 7.0,
      "start_hhmmss": "00:31:23",
      "end_hhmmss": "00:31:30"
    },
    {
      "text": "Se talaron árboles para bloquear las carreteras, se cavaron kilómetros y kilómetros de drincheras",
      "start": 1890.5,
      "duration": 5.279999999999973,
      "start_hhmmss": "00:31:30",
      "end_hhmmss": "00:31:36"
    },
    {
      "text": "y zanjas antitanque. Se colocaron cargas explosivas en fábricas,",
      "start": 1895.78,
      "duration": 5.680000000000064,
      "start_hhmmss": "00:31:36",
      "end_hhmmss": "00:31:41"
    },
    {
      "text": "puentes y edificios públicos preparadas para ser detonadas si los alemanes capturaban",
      "start": 1901.46,
      "duration": 5.279999999999973,
      "start_hhmmss": "00:31:41",
      "end_hhmmss": "00:31:47"
    },
    {
      "text": "la ciudad. El 13 de agosto los alemanes cortaron la",
      "start": 1906.74,
      "duration": 3.9400000000000546,
      "start_hhmmss": "00:31:47",
      "end_hhmmss": "00:31:51"
    },
    {
      "text": "carretera principal entre Leningrado y Moscú, la principal conexión de la ciudad con el",
      "start": 1910.68,
      "duration": 4.579999999999927,
      "start_hhmmss": "00:31:51",
      "end_hhmmss": "00:31:55"
    },
    {
      "text": "resto del mundo. Una semana más tarde alcanzaron las líneas",
      "start": 1915.26,
      "duration": 4.740000000000009,
      "start_hhmmss": "00:31:55",
      "end_hhmmss": "00:32:00"
    },
    {
      "text": "de defensa exteriores de la ciudad y empezaron a estrechar el cerco.",
      "start": 1920.0,
      "duration": 6.7999999999999545,
      "start_hhmmss": "00:32:00",
      "end_hhmmss": "00:32:07"
    },
    {
      "text": "El 1 de septiembre de 1941, tres meses después del comienzo de la invasión y dos años",
      "start": 1926.8,
      "duration": 5.400000000000091,
      "start_hhmmss": "00:32:07",
      "end_hhmmss": "00:32:12"
    },
    {
      "text": "exactos después de la invasión de Polonia, los primeros proyectiles alemanes cayeron",
      "start": 1932.2,
      "duration": 4.839999999999918,
      "start_hhmmss": "00:32:12",
      "end_hhmmss": "00:32:17"
    },
    {
      "text": "sobre Leningrado.",
      "start": 1937.04,
      "duration": 3.0,
      "start_hhmmss": "00:32:17",
      "end_hhmmss": "00:32:20"
    },
    {
      "text": "Dos días más tarde llegó el primer ataque de la luz baje.",
      "start": 1950.0,
      "duration": 7.0,
      "start_hhmmss": "00:32:30",
      "end_hhmmss": "00:32:37"
    },
    {
      "text": "Miles de bombas incendiarias cayeron sobre la ciudad.",
      "start": 1973.72,
      "duration": 3.119999999999891,
      "start_hhmmss": "00:32:54",
      "end_hhmmss": "00:32:57"
    },
    {
      "text": "Durante los dos meses siguientes Leningrado sufrió 272 bombardeos.",
      "start": 1977.24,
      "duration": 5.0,
      "start_hhmmss": "00:32:57",
      "end_hhmmss": "00:33:02"
    },
    {
      "text": "Mientras los rusos estaban atrapados por los continuos ataques, los alemanes acordonaron",
      "start": 1989.6399999999999,
      "duration": 4.360000000000127,
      "start_hhmmss": "00:33:10",
      "end_hhmmss": "00:33:14"
    },
    {
      "text": "sistemáticamente todas las rutas de escape y empezaron a cerrar el cerco.",
      "start": 1994.0,
      "duration": 7.0,
      "start_hhmmss": "00:33:14",
      "end_hhmmss": "00:33:21"
    },
    {
      "text": "Con sus tropas a tan solo 11 kilómetros del centro de Leningrado, Hitler volvió a",
      "start": 2006.84,
      "duration": 7.0,
      "start_hhmmss": "00:33:27",
      "end_hhmmss": "00:33:34"
    },
    {
      "text": "interferir. En otro frustrante cambio de estrategia declaró",
      "start": 2017.8799999999999,
      "duration": 4.600000000000136,
      "start_hhmmss": "00:33:38",
      "end_hhmmss": "00:33:42"
    },
    {
      "text": "que Moscú volvía a ser el objetivo principal. Todas las tropas disponibles debían dirigirse",
      "start": 2022.48,
      "duration": 7.0,
      "start_hhmmss": "00:33:42",
      "end_hhmmss": "00:33:49"
    },
    {
      "text": "hacia el sur. Hitler tenía algo especial pensado para Leningrado.",
      "start": 2029.84,
      "duration": 5.0,
      "start_hhmmss": "00:33:50",
      "end_hhmmss": "00:33:55"
    },
    {
      "text": "Asumiendo que los bombarderos y la artillería de campaña que rodeaba la ciudad podrían",
      "start": 2034.84,
      "duration": 7.0,
      "start_hhmmss": "00:33:55",
      "end_hhmmss": "00:34:02"
    },
    {
      "text": "mantener a raya la población, Hitler declaró que ningún otro alemán perdería la vida",
      "start": 2045.36,
      "duration": 4.839999999999918,
      "start_hhmmss": "00:34:05",
      "end_hhmmss": "00:34:10"
    },
    {
      "text": "en Leningrado. La ciudad sería aislada y abandonada a la",
      "start": 2050.2,
      "duration": 4.119999999999891,
      "start_hhmmss": "00:34:10",
      "end_hhmmss": "00:34:14"
    },
    {
      "text": "mercé del invierno ruso.",
      "start": 2054.3199999999997,
      "duration": 3.0,
      "start_hhmmss": "00:34:14",
      "end_hhmmss": "00:34:17"
    },
    {
      "text": "Con absoluta frialdad, Hitler calculó que una tercera parte de los tres millones de",
      "start": 2065.0,
      "duration": 4.160000000000309,
      "start_hhmmss": "00:34:25",
      "end_hhmmss": "00:34:29"
    },
    {
      "text": "habitantes de la ciudad habría muerto antes de la primavera y después el aumento de las",
      "start": 2069.1600000000003,
      "duration": 4.799999999999727,
      "start_hhmmss": "00:34:29",
      "end_hhmmss": "00:34:34"
    },
    {
      "text": "temperaturas propagaría enfermedades entre los famélicos supervivientes.",
      "start": 2073.96,
      "duration": 7.0,
      "start_hhmmss": "00:34:34",
      "end_hhmmss": "00:34:41"
    },
    {
      "text": "A mediados de octubre, las reservas de combustible y carbón de Leningrado empezaron a agotarse.",
      "start": 2095.84,
      "duration": 7.0,
      "start_hhmmss": "00:34:56",
      "end_hhmmss": "00:35:03"
    },
    {
      "text": "Cuando se congelaron las tuberías, se terminó el agua y también la comida.",
      "start": 2103.6400000000003,
      "duration": 7.0,
      "start_hhmmss": "00:35:04",
      "end_hhmmss": "00:35:11"
    },
    {
      "text": "A principios de noviembre, los que hacían trabajos físicos recibían solamente una",
      "start": 2115.28,
      "duration": 4.119999999999891,
      "start_hhmmss": "00:35:15",
      "end_hhmmss": "00:35:19"
    },
    {
      "text": "ración diaria de 260 gramos de pan, el resto recibía la mitad. Perros, gatos, ratas y",
      "start": 2119.4,
      "duration": 7.0,
      "start_hhmmss": "00:35:19",
      "end_hhmmss": "00:35:26"
    },
    {
      "text": "palomas desaparecieron de las calles, pero la gente seguía muriendo de hambre. Los muertos",
      "start": 2126.4,
      "duration": 7.0,
      "start_hhmmss": "00:35:26",
      "end_hhmmss": "00:35:33"
    },
    {
      "text": "se quedaban donde caían, congelados en la nieve. Los vivos ya no tenían fuerzas para",
      "start": 2133.44,
      "duration": 5.8400000000001455,
      "start_hhmmss": "00:35:33",
      "end_hhmmss": "00:35:39"
    },
    {
      "text": "enterrarlos en la tierra congelada.",
      "start": 2139.28,
      "duration": 5.0,
      "start_hhmmss": "00:35:39",
      "end_hhmmss": "00:35:44"
    },
    {
      "text": "En noviembre murieron 11.000 personas, en diciembre la cifra subió hasta 53.000. En",
      "start": 2145.1600000000003,
      "duration": 7.0,
      "start_hhmmss": "00:35:45",
      "end_hhmmss": "00:35:52"
    },
    {
      "text": "enero empezaron a encontrarse cuerpos a los que les habían cortado pedazos de carne y",
      "start": 2155.4,
      "duration": 5.200000000000273,
      "start_hhmmss": "00:35:55",
      "end_hhmmss": "00:36:01"
    },
    {
      "text": "los niños empezaron a desaparecer de las calles.",
      "start": 2160.6000000000004,
      "duration": 7.0,
      "start_hhmmss": "00:36:01",
      "end_hhmmss": "00:36:08"
    },
    {
      "text": "Mientras Leningrado agonizaba, los nazis continuaban persiguiendo su objetivo de destruir",
      "start": 2167.6,
      "duration": 7.0,
      "start_hhmmss": "00:36:08",
      "end_hhmmss": "00:36:15"
    },
    {
      "text": "Rusia. Si los grupos norte y central se habían visto perjudicados por las intervenciones",
      "start": 2176.56,
      "duration": 7.0,
      "start_hhmmss": "00:36:17",
      "end_hhmmss": "00:36:24"
    },
    {
      "text": "de Hitler, los problemas del grupo sur eran el resultado directo de la determinación",
      "start": 2186.36,
      "duration": 4.959999999999582,
      "start_hhmmss": "00:36:26",
      "end_hhmmss": "00:36:31"
    },
    {
      "text": "soviética. Ucrania tenía vastas reservas de metal de hierro, petróleo, carbón y grano,",
      "start": 2191.32,
      "duration": 6.639999999999873,
      "start_hhmmss": "00:36:31",
      "end_hhmmss": "00:36:38"
    },
    {
      "text": "y Kiev era la llave para entrar en Ucrania.",
      "start": 2197.96,
      "duration": 7.0,
      "start_hhmmss": "00:36:38",
      "end_hhmmss": "00:36:45"
    },
    {
      "text": "El avance alemán sobre Ucrania no empezó hasta nueve días después del avanzadilla",
      "start": 2209.2400000000002,
      "duration": 3.8400000000001455,
      "start_hhmmss": "00:36:49",
      "end_hhmmss": "00:36:53"
    },
    {
      "text": "inicial sobre el norte y el centro de Rusia, en base a la teoría de que las tropas ucranianas",
      "start": 2213.0800000000004,
      "duration": 5.859999999999673,
      "start_hhmmss": "00:36:53",
      "end_hhmmss": "00:36:59"
    },
    {
      "text": "serían transferidas al norte para reforzar las defensas de Moscú.",
      "start": 2218.94,
      "duration": 7.0,
      "start_hhmmss": "00:36:59",
      "end_hhmmss": "00:37:06"
    },
    {
      "text": "Era un plan muy bueno, pero no funcionó. Kiev era un objetivo tan evidente que Stalin",
      "start": 2230.54,
      "duration": 7.0,
      "start_hhmmss": "00:37:11",
      "end_hhmmss": "00:37:18"
    },
    {
      "text": "había asignado 68 de las mejores divisiones rusas para evitar que la ciudad cayeran manos",
      "start": 2242.06,
      "duration": 5.140000000000327,
      "start_hhmmss": "00:37:22",
      "end_hhmmss": "00:37:27"
    },
    {
      "text": "enemigas y debían mantener sus posiciones a toda costa.",
      "start": 2247.2,
      "duration": 6.039999999999964,
      "start_hhmmss": "00:37:27",
      "end_hhmmss": "00:37:33"
    },
    {
      "text": "Desgraciadamente para las tropas soviéticas, los ucranianos odiaban a los comunistas.",
      "start": 2253.24,
      "duration": 5.039999999999964,
      "start_hhmmss": "00:37:33",
      "end_hhmmss": "00:37:38"
    },
    {
      "text": "De hecho, muchos ucranianos veían a los alemanes como liberadores que venían a expulsar a",
      "start": 2258.2799999999997,
      "duration": 4.480000000000018,
      "start_hhmmss": "00:37:38",
      "end_hhmmss": "00:37:43"
    },
    {
      "text": "los despreciables rusos. En consecuencia, los rusos eran atacados tanto por los partisanos",
      "start": 2262.7599999999998,
      "duration": 5.639999999999873,
      "start_hhmmss": "00:37:43",
      "end_hhmmss": "00:37:48"
    },
    {
      "text": "ucranianos como por los alemanes, y se vieron obligados a retirarse.",
      "start": 2268.3999999999996,
      "duration": 7.0,
      "start_hhmmss": "00:37:48",
      "end_hhmmss": "00:37:55"
    },
    {
      "text": "Pero, por una vez, los rusos mantuvieron el orden. Se retiraron de forma estratégica,",
      "start": 2278.2,
      "duration": 7.0,
      "start_hhmmss": "00:37:58",
      "end_hhmmss": "00:38:05"
    },
    {
      "text": "luchando rabiosamente ante el avance de los alemanes.",
      "start": 2288.2799999999997,
      "duration": 7.0,
      "start_hhmmss": "00:38:08",
      "end_hhmmss": "00:38:15"
    },
    {
      "text": "Los alemanes estaban en inferioridad numérica de 2 a 1, y los rusos también contaban con",
      "start": 2297.48,
      "duration": 5.319999999999709,
      "start_hhmmss": "00:38:17",
      "end_hhmmss": "00:38:23"
    },
    {
      "text": "muchos más tanques, más de 2.400 contra 600 pánzers.",
      "start": 2302.8,
      "duration": 7.0,
      "start_hhmmss": "00:38:23",
      "end_hhmmss": "00:38:30"
    },
    {
      "text": "Si los alemanes querían Ucrania, tendrán que luchar por cada centímetro cuadrado.",
      "start": 2314.92,
      "duration": 7.0,
      "start_hhmmss": "00:38:35",
      "end_hhmmss": "00:38:42"
    },
    {
      "text": "A pesar de la resistencia, al cabo de tan solo una semana los alemanes estaban a menos",
      "start": 2324.28,
      "duration": 4.2800000000002,
      "start_hhmmss": "00:38:44",
      "end_hhmmss": "00:38:49"
    },
    {
      "text": "de 160 kilómetros de Kiev, y empezaba a ser evidente que Kiev no podría aguantar.",
      "start": 2328.56,
      "duration": 7.0,
      "start_hhmmss": "00:38:49",
      "end_hhmmss": "00:38:56"
    },
    {
      "text": "El 13 de septiembre, los comandantes rusos rogaron a Stalin que ordenara una retirada.",
      "start": 2336.44,
      "duration": 6.420000000000073,
      "start_hhmmss": "00:38:56",
      "end_hhmmss": "00:39:03"
    },
    {
      "text": "Solo tardó un día en acceder, pero ya era demasiado tarde.",
      "start": 2342.86,
      "duration": 7.0,
      "start_hhmmss": "00:39:03",
      "end_hhmmss": "00:39:10"
    },
    {
      "text": "Atacados por los bombarderos de la Luz Baffe, y atrapados entre los tanques alemanes en",
      "start": 2353.16,
      "duration": 4.119999999999891,
      "start_hhmmss": "00:39:13",
      "end_hhmmss": "00:39:17"
    },
    {
      "text": "la avanzada y el río Nieper, de 800 metros de ancho, el pánico cundió entre la caballería",
      "start": 2357.28,
      "duration": 5.440000000000055,
      "start_hhmmss": "00:39:17",
      "end_hhmmss": "00:39:23"
    },
    {
      "text": "y la infantería, pero consiguieron mantener las posiciones y siguieron luchando dos semanas",
      "start": 2362.7200000000003,
      "duration": 5.480000000000018,
      "start_hhmmss": "00:39:23",
      "end_hhmmss": "00:39:28"
    },
    {
      "text": "más.",
      "start": 2368.2000000000003,
      "duration": 7.0,
      "start_hhmmss": "00:39:28",
      "end_hhmmss": "00:39:35"
    },
    {
      "text": "Cuando Kiev cayó, el suelo estaba repleto de montones de material roto, caballos muertos",
      "start": 2375.2,
      "duration": 7.0,
      "start_hhmmss": "00:39:35",
      "end_hhmmss": "00:39:42"
    },
    {
      "text": "y los cuerpos de cerca de un tercio de millón de soldados rusos.",
      "start": 2390.52,
      "duration": 5.7599999999997635,
      "start_hhmmss": "00:39:51",
      "end_hhmmss": "00:39:56"
    },
    {
      "text": "Cerca de 700.000 más fueron hechos prisioneros.",
      "start": 2396.2799999999997,
      "duration": 3.0,
      "start_hhmmss": "00:39:56",
      "end_hhmmss": "00:39:59"
    },
    {
      "text": "Las riquezas de Ucrania estaban en manos de Alemania, pero sorprendentemente Hitler volvió",
      "start": 2399.28,
      "duration": 7.0,
      "start_hhmmss": "00:39:59",
      "end_hhmmss": "00:40:06"
    },
    {
      "text": "a estropear su victoria. Todas las unidades que formaban el grupo central debían regresar",
      "start": 2411.76,
      "duration": 5.639999999999873,
      "start_hhmmss": "00:40:12",
      "end_hhmmss": "00:40:17"
    },
    {
      "text": "al norte para unirse a sus compañeros que habían sido expulsados de Leningrado.",
      "start": 2417.4,
      "duration": 6.119999999999891,
      "start_hhmmss": "00:40:17",
      "end_hhmmss": "00:40:24"
    },
    {
      "text": "La Operación Tifón, el ataque final a Moscú, empezaría el 2 de octubre.",
      "start": 2423.52,
      "duration": 7.0,
      "start_hhmmss": "00:40:24",
      "end_hhmmss": "00:40:31"
    },
    {
      "text": "El gran movimiento de los alemanes hacia el corazón de Rusia dejó muy claras sus intenciones.",
      "start": 2432.88,
      "duration": 7.0,
      "start_hhmmss": "00:40:33",
      "end_hhmmss": "00:40:40"
    },
    {
      "text": "En Moscú, 800.000 tropas regulares fueron asignadas a la defensa de la ciudad. A ello",
      "start": 2441.8,
      "duration": 5.559999999999945,
      "start_hhmmss": "00:40:42",
      "end_hhmmss": "00:40:47"
    },
    {
      "text": "se unieron cinco divisiones más formadas precipitadamente con trabajadores industriales.",
      "start": 2447.36,
      "duration": 4.760000000000218,
      "start_hhmmss": "00:40:47",
      "end_hhmmss": "00:40:52"
    },
    {
      "text": "Además, 90.000 soldados más llegaron de Siberia.",
      "start": 2452.1200000000003,
      "duration": 7.0,
      "start_hhmmss": "00:40:52",
      "end_hhmmss": "00:40:59"
    },
    {
      "text": "Más de medio millón de moscovitas, mujeres, tenderos y estudiantes fueron destinados a",
      "start": 2468.6400000000003,
      "duration": 5.079999999999927,
      "start_hhmmss": "00:41:09",
      "end_hhmmss": "00:41:14"
    },
    {
      "text": "la construcción de barricadas. En cuestión de semanas habían cavado más de 100 kilómetros",
      "start": 2473.72,
      "duration": 6.0,
      "start_hhmmss": "00:41:14",
      "end_hhmmss": "00:41:20"
    },
    {
      "text": "de zanjas antitanque, 8.000 kilómetros de trincheras y habían levantado 72 kilómetros",
      "start": 2479.72,
      "duration": 6.239999999999782,
      "start_hhmmss": "00:41:20",
      "end_hhmmss": "00:41:26"
    },
    {
      "text": "de barricadas. Las fábricas se desmontaron y se cargaron en trenes para transportarlas",
      "start": 2485.9599999999996,
      "duration": 5.800000000000182,
      "start_hhmmss": "00:41:26",
      "end_hhmmss": "00:41:32"
    },
    {
      "text": "hacia el este fuera del alcance de los alemanes.",
      "start": 2491.7599999999998,
      "duration": 7.0,
      "start_hhmmss": "00:41:32",
      "end_hhmmss": "00:41:39"
    },
    {
      "text": "Para cuando el grupo central se había vuelto a reunir, más de 15 ejércitos rusos habían",
      "start": 2499.76,
      "duration": 5.119999999999891,
      "start_hhmmss": "00:41:40",
      "end_hhmmss": "00:41:45"
    },
    {
      "text": "tomado posiciones a lo largo de una línea defensiva de más de 400 kilómetros de longitud.",
      "start": 2504.88,
      "duration": 7.0,
      "start_hhmmss": "00:41:45",
      "end_hhmmss": "00:41:52"
    },
    {
      "text": "A pesar de la superioridad numérica, las defensas rusas estaban muy mal equipadas, tenían menos",
      "start": 2513.0,
      "duration": 5.360000000000127,
      "start_hhmmss": "00:41:53",
      "end_hhmmss": "00:41:58"
    },
    {
      "text": "de 800 tanques y solamente 365 aviones para defender la capital.",
      "start": 2518.36,
      "duration": 5.0,
      "start_hhmmss": "00:41:58",
      "end_hhmmss": "00:42:03"
    },
    {
      "text": "El batallón medio ruso, formado por 675 hombres, tenía tan solo 300 rifles, 120 granadas de",
      "start": 2524.36,
      "duration": 7.0,
      "start_hhmmss": "00:42:04",
      "end_hhmmss": "00:42:11"
    },
    {
      "text": "mano, nueve ametralladoras y 150 pistolas. El resto debía limitarse a conseguir botellas",
      "start": 2532.32,
      "duration": 6.639999999999873,
      "start_hhmmss": "00:42:12",
      "end_hhmmss": "00:42:19"
    },
    {
      "text": "y petróleo para hacer cócteles molotov. Parecía que Moscú también iba a caer en",
      "start": 2538.96,
      "duration": 5.880000000000109,
      "start_hhmmss": "00:42:19",
      "end_hhmmss": "00:42:25"
    },
    {
      "text": "manos de Hitler. El ataque a Moscú empezó según la Comisión",
      "start": 2544.84,
      "duration": 7.0,
      "start_hhmmss": "00:42:25",
      "end_hhmmss": "00:42:32"
    },
    {
      "text": "de los Planes de Hitler el 2 de octubre con una maniobra en pinza sobre las defensas rusas",
      "start": 2553.36,
      "duration": 4.8400000000001455,
      "start_hhmmss": "00:42:33",
      "end_hhmmss": "00:42:38"
    },
    {
      "text": "del oeste de la ciudad. En tres días las unidades Panzer estaban a",
      "start": 2558.2000000000003,
      "duration": 7.0,
      "start_hhmmss": "00:42:38",
      "end_hhmmss": "00:42:45"
    },
    {
      "text": "350 kilómetros de la ciudad, presionando las defensas más periféricas del ejército",
      "start": 2569.0,
      "duration": 5.599999999999909,
      "start_hhmmss": "00:42:49",
      "end_hhmmss": "00:42:55"
    },
    {
      "text": "ruso. En diez días de sangrientos combates, más",
      "start": 2574.6,
      "duration": 7.0,
      "start_hhmmss": "00:42:55",
      "end_hhmmss": "00:43:02"
    },
    {
      "text": "de 650.000 rusos cayeron prisioneros. Toda la primera línea de las defensas de Moscú",
      "start": 2581.88,
      "duration": 6.279999999999745,
      "start_hhmmss": "00:43:02",
      "end_hhmmss": "00:43:08"
    },
    {
      "text": "y gran parte de la segunda fue completamente destruida.",
      "start": 2588.16,
      "duration": 7.0,
      "start_hhmmss": "00:43:08",
      "end_hhmmss": "00:43:15"
    },
    {
      "text": "Una semana más tarde los rusos organizaron su primera gran contraofensiva. Una interminable",
      "start": 2600.36,
      "duration": 4.919999999999618,
      "start_hhmmss": "00:43:20",
      "end_hhmmss": "00:43:25"
    },
    {
      "text": "marea de tanques, cohetes, campos de minas y artillería atacó a muerte a los invasores.",
      "start": 2605.28,
      "duration": 7.0,
      "start_hhmmss": "00:43:25",
      "end_hhmmss": "00:43:32"
    },
    {
      "text": "Pero a pesar de una lista de bajas de más de medio millón de hombres, Hitler estaba",
      "start": 2617.28,
      "duration": 3.6799999999998363,
      "start_hhmmss": "00:43:37",
      "end_hhmmss": "00:43:41"
    },
    {
      "text": "determinado a tomar Moscú. Cuando las tropas alemanas se acercaron a",
      "start": 2620.96,
      "duration": 7.0,
      "start_hhmmss": "00:43:41",
      "end_hhmmss": "00:43:48"
    },
    {
      "text": "110 kilómetros de Moscú, el pánico se apoderó de la ciudad.",
      "start": 2627.96,
      "duration": 7.0,
      "start_hhmmss": "00:43:48",
      "end_hhmmss": "00:43:55"
    },
    {
      "text": "La gente huía en todas direcciones. En cuestión de horas las carreteras estaban colapsadas",
      "start": 2642.84,
      "duration": 4.359999999999673,
      "start_hhmmss": "00:44:03",
      "end_hhmmss": "00:44:07"
    },
    {
      "text": "por coches gubernamentales, peatones y coches de caballos. Se produjeron disturbios en las",
      "start": 2647.2,
      "duration": 5.120000000000346,
      "start_hhmmss": "00:44:07",
      "end_hhmmss": "00:44:12"
    },
    {
      "text": "principales estaciones de tren. Las tiendas y las casas eran saqueadas y se hizo imposible",
      "start": 2652.32,
      "duration": 5.079999999999927,
      "start_hhmmss": "00:44:12",
      "end_hhmmss": "00:44:17"
    },
    {
      "text": "restablecer el orden. La policía también había huido.",
      "start": 2657.4,
      "duration": 5.2800000000002,
      "start_hhmmss": "00:44:17",
      "end_hhmmss": "00:44:23"
    },
    {
      "text": "El 19 de octubre, después de tres días de disturbios descontrolados, Joseph Stalin impuso",
      "start": 2662.6800000000003,
      "duration": 4.799999999999727,
      "start_hhmmss": "00:44:23",
      "end_hhmmss": "00:44:27"
    },
    {
      "text": "la ley marcial. Cualquiera que fuera visto saqueando, violando",
      "start": 2667.48,
      "duration": 5.599999999999909,
      "start_hhmmss": "00:44:27",
      "end_hhmmss": "00:44:33"
    },
    {
      "text": "el toque de queda, provocando disturbios o intentando abandonar la ciudad, sería ejecutado.",
      "start": 2673.08,
      "duration": 7.0,
      "start_hhmmss": "00:44:33",
      "end_hhmmss": "00:44:40"
    },
    {
      "text": "Si los rusos no podían escapar de Moscú, a los alemanes también les estaba costando",
      "start": 2680.08,
      "duration": 7.0,
      "start_hhmmss": "00:44:40",
      "end_hhmmss": "00:44:47"
    },
    {
      "text": "mucho encontrar una vía de entrada. Solo había tres carreteras pavimentadas que",
      "start": 2690.56,
      "duration": 7.0,
      "start_hhmmss": "00:44:51",
      "end_hhmmss": "00:44:58"
    },
    {
      "text": "llevaban a la capital, insuficientes para las 69 divisiones que se necesitaban para",
      "start": 2698.12,
      "duration": 4.920000000000073,
      "start_hhmmss": "00:44:58",
      "end_hhmmss": "00:45:03"
    },
    {
      "text": "organizar un ataque efectivo. La infantería y la policía se organizaron",
      "start": 2703.04,
      "duration": 7.0,
      "start_hhmmss": "00:45:03",
      "end_hhmmss": "00:45:10"
    },
    {
      "text": "y la artillería tenían que abrirse paso a través de la campiña, a través de campos",
      "start": 2710.08,
      "duration": 3.800000000000182,
      "start_hhmmss": "00:45:10",
      "end_hhmmss": "00:45:14"
    },
    {
      "text": "y praderas silvestres. La madre rusia era, por lo menos, poco hospitalaria.",
      "start": 2713.88,
      "duration": 7.0,
      "start_hhmmss": "00:45:14",
      "end_hhmmss": "00:45:21"
    },
    {
      "text": "Cuando el clima era seco, las nubes de polvo ahogaban a hombres y máquinas. Y durante",
      "start": 2723.44,
      "duration": 4.239999999999782,
      "start_hhmmss": "00:45:23",
      "end_hhmmss": "00:45:28"
    },
    {
      "text": "la última semana de octubre, cuando los alemanes avanzaban hacia Moscú, empezó a llover.",
      "start": 2727.68,
      "duration": 7.0,
      "start_hhmmss": "00:45:28",
      "end_hhmmss": "00:45:35"
    },
    {
      "text": "Las nubes que trajeron la lluvia cubrieron los cielos y obligaron a los aviones alemanes",
      "start": 2735.1,
      "duration": 4.199999999999818,
      "start_hhmmss": "00:45:35",
      "end_hhmmss": "00:45:39"
    },
    {
      "text": "a aterrizar. Como la lluvia no paraba, las carreteras y los campos se convirtieron en",
      "start": 2739.3,
      "duration": 7.0,
      "start_hhmmss": "00:45:39",
      "end_hhmmss": "00:45:46"
    },
    {
      "text": "mares de barro que se tragaban las botas de un hombre tras otro. Los camiones se hundían",
      "start": 2754.1800000000003,
      "duration": 5.359999999999673,
      "start_hhmmss": "00:45:54",
      "end_hhmmss": "00:46:00"
    },
    {
      "text": "hasta los ejes y los caballos hasta la barriga. Los tanques de combustible quedaban atrapados",
      "start": 2759.54,
      "duration": 7.0,
      "start_hhmmss": "00:46:00",
      "end_hhmmss": "00:46:07"
    },
    {
      "text": "y los vehículos eran abandonados cuando se quedaban sin gasolina. Los ríos crecían",
      "start": 2766.88,
      "duration": 5.139999999999873,
      "start_hhmmss": "00:46:07",
      "end_hhmmss": "00:46:12"
    },
    {
      "text": "y se llevaban los puentes mientras vehículos enteros desaparecían en el Lodazán.",
      "start": 2772.02,
      "duration": 7.0,
      "start_hhmmss": "00:46:12",
      "end_hhmmss": "00:46:19"
    },
    {
      "text": "El avance relámpago de la Blitzkrieg redujo el paso a 5 kilómetros al día.",
      "start": 2784.54,
      "duration": 7.0,
      "start_hhmmss": "00:46:25",
      "end_hhmmss": "00:46:32"
    },
    {
      "text": "Una helada repentina la noche del 6 de noviembre dio a la pesada maquinaria de guerra alemana",
      "start": 2792.34,
      "duration": 7.0,
      "start_hhmmss": "00:46:32",
      "end_hhmmss": "00:46:39"
    },
    {
      "text": "una última oportunidad de liberarse y hacer una última avanzadilla hacia Moscú. Mientras",
      "start": 2800.3,
      "duration": 5.819999999999709,
      "start_hhmmss": "00:46:40",
      "end_hhmmss": "00:46:46"
    },
    {
      "text": "los alemanes despegaban su equipo del barro helado, la temperatura empezó a descender.",
      "start": 2806.12,
      "duration": 7.0,
      "start_hhmmss": "00:46:46",
      "end_hhmmss": "00:46:53"
    },
    {
      "text": "Cuando el termómetro bajó empezó a nevar. El 12 de noviembre la temperatura se despegó",
      "start": 2813.58,
      "duration": 7.0,
      "start_hhmmss": "00:46:54",
      "end_hhmmss": "00:47:01"
    },
    {
      "text": "y alcanzó los 12 grados bajo cero. Al día siguiente bajó hasta los 20 grados bajo cero",
      "start": 2821.9,
      "duration": 6.0,
      "start_hhmmss": "00:47:02",
      "end_hhmmss": "00:47:08"
    },
    {
      "text": "y el 4 de diciembre ya había alcanzado los 35 bajo cero. El alto mando alemán aceptó",
      "start": 2827.9,
      "duration": 6.119999999999891,
      "start_hhmmss": "00:47:08",
      "end_hhmmss": "00:47:14"
    },
    {
      "text": "que Moscú no sería ocupada antes de Navidad. Los tanques debían estar continuamente en",
      "start": 2834.02,
      "duration": 7.0,
      "start_hhmmss": "00:47:14",
      "end_hhmmss": "00:47:21"
    },
    {
      "text": "marcha para no helarse. Cuando se quedaban sin combustible se congelaban. Los caballos",
      "start": 2843.18,
      "duration": 7.0,
      "start_hhmmss": "00:47:23",
      "end_hhmmss": "00:47:30"
    },
    {
      "text": "morían congelados. Las calderas de las locomotoras se congelaban y explotaban. Los heridos que",
      "start": 2850.54,
      "duration": 7.0,
      "start_hhmmss": "00:47:31",
      "end_hhmmss": "00:47:38"
    },
    {
      "text": "yacían en los trenes hospital morían congelados a centenares. Los rifles y las ametralladoras",
      "start": 2858.94,
      "duration": 6.199999999999818,
      "start_hhmmss": "00:47:39",
      "end_hhmmss": "00:47:45"
    },
    {
      "text": "no funcionaban puesto que el aceite lubricante se congelaba y la artillería de campaña",
      "start": 2865.14,
      "duration": 4.559999999999945,
      "start_hhmmss": "00:47:45",
      "end_hhmmss": "00:47:50"
    },
    {
      "text": "explotaba cuando su mecanismo de retroceso se atascaba por el frío. Los clavos de acero",
      "start": 2869.7,
      "duration": 6.619999999999891,
      "start_hhmmss": "00:47:50",
      "end_hhmmss": "00:47:56"
    },
    {
      "text": "de las botas militares estaban tan fríos que podían perforar por congelación el",
      "start": 2876.32,
      "duration": 4.360000000000127,
      "start_hhmmss": "00:47:56",
      "end_hhmmss": "00:48:01"
    },
    {
      "text": "pie de un hombre y dejarle lisiado de por vida y quedarse dormido significaba la muerte.",
      "start": 2880.6800000000003,
      "duration": 7.0,
      "start_hhmmss": "00:48:01",
      "end_hhmmss": "00:48:08"
    },
    {
      "text": "A tan solo 30 kilómetros de Moscú pero a más de 1600 de Berlín la blitzkrieg alemana",
      "start": 2888.2000000000003,
      "duration": 5.359999999999673,
      "start_hhmmss": "00:48:08",
      "end_hhmmss": "00:48:14"
    },
    {
      "text": "quedó totalmente paralizada. Los generales suplicaron a Hitler que les permitiera retirarse",
      "start": 2893.56,
      "duration": 7.0,
      "start_hhmmss": "00:48:14",
      "end_hhmmss": "00:48:21"
    },
    {
      "text": "de posiciones defendibles para pasar el invierno. Pero no importa lo crudo que fuera el informe,",
      "start": 2900.56,
      "duration": 6.1599999999998545,
      "start_hhmmss": "00:48:21",
      "end_hhmmss": "00:48:27"
    },
    {
      "text": "Hitler era inflexible. Moscú debía caer. En un intento desesperado de rodear Moscú",
      "start": 2906.72,
      "duration": 7.0,
      "start_hhmmss": "00:48:27",
      "end_hhmmss": "00:48:34"
    },
    {
      "text": "tres de las unidades Panzer que quedaban se dirigieron hacia el noreste y el oeste de",
      "start": 2924.6,
      "duration": 4.360000000000127,
      "start_hhmmss": "00:48:45",
      "end_hhmmss": "00:48:49"
    },
    {
      "text": "la ciudad. A tan solo 16 kilómetros de Moscú las tropas encargadas de destruir una estación",
      "start": 2928.96,
      "duration": 7.0,
      "start_hhmmss": "00:48:49",
      "end_hhmmss": "00:48:56"
    },
    {
      "text": "de tren vieron las cúpulas doradas de la catedral de San Basilio brillando bajo el",
      "start": 2939.04,
      "duration": 4.440000000000055,
      "start_hhmmss": "00:48:59",
      "end_hhmmss": "00:49:03"
    },
    {
      "text": "frío sol invernal. Era lo más cerca que la Alemania nazi llegaría jamás de su objetivo.",
      "start": 2943.48,
      "duration": 7.0,
      "start_hhmmss": "00:49:03",
      "end_hhmmss": "00:49:10"
    },
    {
      "text": "Durante la fútil avanzadilla final hacia Moscú los exhaustos alemanes perdieron a",
      "start": 2950.48,
      "duration": 7.0,
      "start_hhmmss": "00:49:10",
      "end_hhmmss": "00:49:17"
    },
    {
      "text": "15.000 hombres más mientras los rusos reunieron 50 nuevas divisiones.",
      "start": 2959.44,
      "duration": 7.0,
      "start_hhmmss": "00:49:19",
      "end_hhmmss": "00:49:26"
    },
    {
      "text": "El ataque sobre Moscú había costado a los alemanes casi un cuarto de millón de bajas",
      "start": 2969.88,
      "duration": 4.920000000000073,
      "start_hhmmss": "00:49:30",
      "end_hhmmss": "00:49:35"
    },
    {
      "text": "y les había proporcionado solo 160 kilómetros de territorio ruso. Se habían perdido dos",
      "start": 2974.8,
      "duration": 7.0,
      "start_hhmmss": "00:49:35",
      "end_hhmmss": "00:49:42"
    },
    {
      "text": "terceras partes del total de tanques alemanes y ahora los rusos se estaban preparando para",
      "start": 2988.1600000000003,
      "duration": 5.0,
      "start_hhmmss": "00:49:48",
      "end_hhmmss": "00:49:53"
    },
    {
      "text": "atacar.",
      "start": 2993.1600000000003,
      "duration": 1.0,
      "start_hhmmss": "00:49:53",
      "end_hhmmss": "00:49:54"
    },
    {
      "text": "Los rusos se prepararon para atacar. Los rusos se prepararon para atacar.",
      "start": 2994.1600000000003,
      "duration": 7.0,
      "start_hhmmss": "00:49:54",
      "end_hhmmss": "00:50:01"
    },
    {
      "text": "La movilización fue el 5 de diciembre cuando 700.000 rusos con el apoyo de 8.000 piezas",
      "start": 3004.8,
      "duration": 7.0,
      "start_hhmmss": "00:50:05",
      "end_hhmmss": "00:50:12"
    },
    {
      "text": "de artillería pesada se lanzaron sobre los alemanes medio congelados con la furia de",
      "start": 3013.6400000000003,
      "duration": 5.0,
      "start_hhmmss": "00:50:14",
      "end_hhmmss": "00:50:19"
    },
    {
      "text": "los cosacos. No había absolutamente nada que los alemanes",
      "start": 3018.6400000000003,
      "duration": 7.0,
      "start_hhmmss": "00:50:19",
      "end_hhmmss": "00:50:26"
    },
    {
      "text": "pudieran hacer para defenderse.",
      "start": 3025.64,
      "duration": 7.0,
      "start_hhmmss": "00:50:26",
      "end_hhmmss": "00:50:33"
    },
    {
      "text": "Diez días más tarde las unidades siberianas rompieron las filas alemanas diezmando dos",
      "start": 3032.64,
      "duration": 7.0,
      "start_hhmmss": "00:50:33",
      "end_hhmmss": "00:50:40"
    },
    {
      "text": "divisiones Panzer y dejando su resto repartidos a lo largo de 40 kilómetros de carretera.",
      "start": 3040.3599999999997,
      "duration": 7.0,
      "start_hhmmss": "00:50:40",
      "end_hhmmss": "00:50:47"
    },
    {
      "text": "A lo largo de los 1.290 kilómetros de frente ruso las tropas alemanas perdieron el rumbo.",
      "start": 3047.36,
      "duration": 7.0,
      "start_hhmmss": "00:50:47",
      "end_hhmmss": "00:50:54"
    },
    {
      "text": "Hitler y su estado mayor habían abandonado los principios según los que se regía la",
      "start": 3066.76,
      "duration": 4.0,
      "start_hhmmss": "00:51:07",
      "end_hhmmss": "00:51:11"
    },
    {
      "text": "Blitzkrieg. Ataques rápidos y profundos que podían derrotar al enemigo en cuestión de",
      "start": 3070.76,
      "duration": 5.119999999999891,
      "start_hhmmss": "00:51:11",
      "end_hhmmss": "00:51:16"
    },
    {
      "text": "días o semanas. La teoría de la Blitzkrieg no podía soportar batallas prolongadas y",
      "start": 3075.88,
      "duration": 7.0,
      "start_hhmmss": "00:51:16",
      "end_hhmmss": "00:51:23"
    },
    {
      "text": "Rusia era demasiado vasta para una victoria rápida.",
      "start": 3085.44,
      "duration": 7.0,
      "start_hhmmss": "00:51:25",
      "end_hhmmss": "00:51:32"
    },
    {
      "text": "Por primera vez desde que Adolf Hitler había subido al poder hacía más de siete años",
      "start": 3096.76,
      "duration": 5.059999999999945,
      "start_hhmmss": "00:51:37",
      "end_hhmmss": "00:51:42"
    },
    {
      "text": "el ejército alemán iniciaba una retirada. Avanzando con dificultad a través de los",
      "start": 3101.94,
      "duration": 7.0,
      "start_hhmmss": "00:51:42",
      "end_hhmmss": "00:51:49"
    },
    {
      "text": "desiertos helados de Rusia Occidental abandonaron tanques, aviones, hombres y la esperanza.",
      "start": 3110.6200000000003,
      "duration": 7.0,
      "start_hhmmss": "00:51:51",
      "end_hhmmss": "00:51:58"
    },
    {
      "text": "Deberían pasar tres años más antes de que los últimos alemanes salieran de Rusia.",
      "start": 3117.62,
      "duration": 7.0,
      "start_hhmmss": "00:51:58",
      "end_hhmmss": "00:52:05"
    },
    {
      "text": "El sitio de Leningrado fue levantado por fin el 27 de enero de 1944 después de 890 días",
      "start": 3132.54,
      "duration": 7.0,
      "start_hhmmss": "00:52:13",
      "end_hhmmss": "00:52:20"
    },
    {
      "text": "de bombardeos constantes. La mitad de los tres millones de habitantes de la ciudad murieron",
      "start": 3140.42,
      "duration": 6.7599999999997635,
      "start_hhmmss": "00:52:20",
      "end_hhmmss": "00:52:27"
    },
    {
      "text": "defendiéndola. El avance de los rusos no se detuvo hasta que las tropas soviéticas",
      "start": 3147.18,
      "duration": 7.0,
      "start_hhmmss": "00:52:27",
      "end_hhmmss": "00:52:34"
    },
    {
      "text": "se encontraron con sus camaradas, las potencias aliadas de Gran Bretaña, Francia y Estados",
      "start": 3160.02,
      "duration": 5.799999999999727,
      "start_hhmmss": "00:52:40",
      "end_hhmmss": "00:52:46"
    },
    {
      "text": "Unidos en las ruinas carbonizadas del Berlín de Hitler en mayo de 1945. Cuando la Alemania",
      "start": 3165.8199999999997,
      "duration": 7.0,
      "start_hhmmss": "00:52:46",
      "end_hhmmss": "00:52:53"
    },
    {
      "text": "nazi por fin se derrumbó en mayo de 1945 había dejado un legado de destrucción por",
      "start": 3173.5,
      "duration": 5.760000000000218,
      "start_hhmmss": "00:52:54",
      "end_hhmmss": "00:52:59"
    },
    {
      "text": "todo el mundo. Más de 40 millones de hombres, mujeres y niños perdieron la vida y más",
      "start": 3179.26,
      "duration": 7.0,
      "start_hhmmss": "00:52:59",
      "end_hhmmss": "00:53:06"
    },
    {
      "text": "de la mitad eran rusos. Esto y solo esto era el legado de Adolf Hitler y su sueño perturbado",
      "start": 3186.56,
      "duration": 7.0,
      "start_hhmmss": "00:53:07",
      "end_hhmmss": "00:53:14"
    },
    {
      "text": "de dominar el mundo gracias a la Blitzkrieg.",
      "start": 3202.82,
      "duration": 3.119999999999891,
      "start_hhmmss": "00:53:23",
      "end_hhmmss": "00:53:26"
    }
  ]
}